{"build/.DS_Store":"2015-03-19T08:33:53.000Z","build/admin/.DS_Store":"2015-03-19T08:31:48.000Z","build/admin/index.html":"2015-03-20T08:17:35.000Z","build/admin/lock.html":"2015-03-20T08:17:35.000Z","build/admin/login.html":"2015-03-20T08:17:35.000Z","build/admin/pages/.DS_Store":"2015-03-19T08:30:32.000Z","build/admin/pages/calendar.html":"2015-03-20T08:17:35.000Z","build/admin/pages/empty.html":"2015-03-20T08:17:35.000Z","build/admin/pages/mailbox.html":"2015-03-20T08:17:35.000Z","build/admin/pages/widgets.html":"2015-03-20T08:17:35.000Z","build/admin/pages/UI/buttons.html":"2015-03-20T08:17:35.000Z","build/admin/pages/UI/empty.html":"2015-03-20T08:17:35.000Z","build/admin/pages/UI/general.html":"2015-03-20T08:17:35.000Z","build/admin/pages/UI/icons.html":"2015-03-20T08:17:35.000Z","build/admin/pages/UI/jquery-ui.html":"2015-03-20T08:17:35.000Z","build/admin/pages/UI/sliders.html":"2015-03-20T08:17:35.000Z","build/admin/pages/UI/timeline.html":"2015-03-20T08:17:35.000Z","build/admin/pages/charts/empty.html":"2015-03-20T08:17:35.000Z","build/admin/pages/charts/flot.html":"2015-03-20T08:17:35.000Z","build/admin/pages/charts/inline.html":"2015-03-20T08:17:35.000Z","build/admin/pages/charts/morris.html":"2015-03-20T08:17:35.000Z","build/admin/pages/examples/404.html":"2015-03-20T08:17:35.000Z","build/admin/pages/examples/500.html":"2015-03-20T08:17:35.000Z","build/admin/pages/examples/blank.html":"2015-03-20T08:17:35.000Z","build/admin/pages/examples/invoice.html":"2015-03-20T08:17:35.000Z","build/admin/pages/examples/lockscreen.html":"2015-03-20T08:17:35.000Z","build/admin/pages/examples/login.html":"2015-03-20T08:17:35.000Z","build/admin/pages/examples/register.html":"2015-03-20T08:17:35.000Z","build/admin/pages/forms/advanced.html":"2015-03-20T08:17:35.000Z","build/admin/pages/forms/editors.html":"2015-03-20T08:17:35.000Z","build/admin/pages/forms/empty.html":"2015-03-20T08:17:35.000Z","build/admin/pages/forms/general.html":"2015-03-20T08:17:35.000Z","build/admin/pages/tables/data.html":"2015-03-20T08:17:35.000Z","build/admin/pages/tables/empty.html":"2015-03-20T08:17:35.000Z","build/admin/pages/tables/simple.html":"2015-03-20T08:17:35.000Z","build/assets/.DS_Store":"2015-03-19T08:33:33.000Z","build/assets/api/topic/create.txt":"2015-03-20T08:17:32.000Z","build/assets/api/topic/delete.txt":"2015-03-20T08:17:32.000Z","build/assets/api/topic/get.txt":"2015-03-20T08:17:32.000Z","build/assets/api/topic/list.txt":"2015-03-20T08:17:32.000Z","build/assets/api/topic/search.txt":"2015-03-20T08:17:32.000Z","build/assets/api/topic/update.txt":"2015-03-20T08:17:32.000Z","build/assets/api/topicType/create.txt":"2015-03-20T08:17:32.000Z","build/assets/api/topicType/delete.txt":"2015-03-20T08:17:32.000Z","build/assets/api/topicType/get.txt":"2015-03-20T08:17:32.000Z","build/assets/api/topicType/list.txt":"2015-03-20T08:17:32.000Z","build/assets/api/topicType/search.txt":"2015-03-20T08:17:32.000Z","build/assets/api/topicType/update.txt":"2015-03-20T08:17:32.000Z","build/assets/api/user/create.txt":"2015-03-20T08:17:32.000Z","build/assets/api/user/delete.txt":"2015-03-20T08:17:32.000Z","build/assets/api/user/get.txt":"2015-03-20T08:17:32.000Z","build/assets/api/user/list.txt":"2015-03-20T08:17:32.000Z","build/assets/api/user/search.txt":"2015-03-20T08:17:32.000Z","build/assets/api/user/update.txt":"2015-03-20T08:17:32.000Z","build/assets/api/user/validate.txt":"2015-03-20T08:17:32.000Z","build/assets/css/AdminLTE.css":"2015-03-20T08:17:32.000Z","build/assets/css/login.css":"2015-03-20T08:17:33.000Z","build/assets/css/bootstrap-slider/slider.css":"2015-03-20T08:17:32.000Z","build/assets/css/bootstrap-wysihtml5/bootstrap3-wysihtml5.css":"2015-03-20T08:17:32.000Z","build/assets/css/bootstrap-wysihtml5/bootstrap3-wysihtml5.min.css":"2015-03-20T08:17:32.000Z","build/assets/css/colorpicker/bootstrap-colorpicker.css":"2015-03-20T08:17:32.000Z","build/assets/css/colorpicker/bootstrap-colorpicker.min.css":"2015-03-20T08:17:32.000Z","build/assets/css/datatables/dataTables.bootstrap.css":"2015-03-20T08:17:32.000Z","build/assets/css/datatables/images/sort_asc.png":"2015-03-20T08:17:32.000Z","build/assets/css/datatables/images/sort_asc_disabled.png":"2015-03-20T08:17:32.000Z","build/assets/css/datatables/images/sort_both.png":"2015-03-20T08:17:32.000Z","build/assets/css/datatables/images/sort_desc.png":"2015-03-20T08:17:32.000Z","build/assets/css/datatables/images/sort_desc_disabled.png":"2015-03-20T08:17:32.000Z","build/assets/css/datepicker/datepicker3.css":"2015-03-20T08:17:32.000Z","build/assets/css/daterangepicker/daterangepicker-bs3.css":"2015-03-20T08:17:32.000Z","build/assets/css/iCheck/all.css":"2015-03-20T08:17:32.000Z","build/assets/css/iCheck/flat/_all.css":"2015-03-20T08:17:32.000Z","build/assets/css/iCheck/flat/aero.css":"2015-03-20T08:17:32.000Z","build/assets/css/iCheck/flat/aero.png":"2015-03-20T08:17:32.000Z","build/assets/css/iCheck/flat/aero@2x.png":"2015-03-20T08:17:32.000Z","build/assets/css/iCheck/flat/blue.css":"2015-03-20T08:17:32.000Z","build/assets/css/iCheck/flat/blue.png":"2015-03-20T08:17:32.000Z","build/assets/css/iCheck/flat/blue@2x.png":"2015-03-20T08:17:32.000Z","build/assets/css/iCheck/flat/flat.css":"2015-03-20T08:17:32.000Z","build/assets/css/iCheck/flat/flat.png":"2015-03-20T08:17:32.000Z","build/assets/css/iCheck/flat/flat@2x.png":"2015-03-20T08:17:32.000Z","build/assets/css/iCheck/flat/green.css":"2015-03-20T08:17:32.000Z","build/assets/css/iCheck/flat/green.png":"2015-03-20T08:17:32.000Z","build/assets/css/iCheck/flat/green@2x.png":"2015-03-20T08:17:32.000Z","build/assets/css/iCheck/flat/grey.css":"2015-03-20T08:17:32.000Z","build/assets/css/iCheck/flat/grey.png":"2015-03-20T08:17:32.000Z","build/assets/css/iCheck/flat/grey@2x.png":"2015-03-20T08:17:32.000Z","build/assets/css/iCheck/flat/orange.css":"2015-03-20T08:17:32.000Z","build/assets/css/iCheck/flat/orange.png":"2015-03-20T08:17:32.000Z","build/assets/css/iCheck/flat/orange@2x.png":"2015-03-20T08:17:32.000Z","build/assets/css/iCheck/flat/pink.css":"2015-03-20T08:17:32.000Z","build/assets/css/iCheck/flat/pink.png":"2015-03-20T08:17:32.000Z","build/assets/css/iCheck/flat/pink@2x.png":"2015-03-20T08:17:32.000Z","build/assets/css/iCheck/flat/purple.css":"2015-03-20T08:17:32.000Z","build/assets/css/iCheck/flat/purple.png":"2015-03-20T08:17:32.000Z","build/assets/css/iCheck/flat/purple@2x.png":"2015-03-20T08:17:32.000Z","build/assets/css/iCheck/flat/red.css":"2015-03-20T08:17:32.000Z","build/assets/css/iCheck/flat/red.png":"2015-03-20T08:17:32.000Z","build/assets/css/iCheck/flat/red@2x.png":"2015-03-20T08:17:32.000Z","build/assets/css/iCheck/flat/yellow.css":"2015-03-20T08:17:32.000Z","build/assets/css/iCheck/flat/yellow.png":"2015-03-20T08:17:32.000Z","build/assets/css/iCheck/flat/yellow@2x.png":"2015-03-20T08:17:32.000Z","build/assets/css/iCheck/futurico/futurico.css":"2015-03-20T08:17:32.000Z","build/assets/css/iCheck/futurico/futurico.png":"2015-03-20T08:17:32.000Z","build/assets/css/iCheck/futurico/futurico@2x.png":"2015-03-20T08:17:32.000Z","build/assets/css/iCheck/line/_all.css":"2015-03-20T08:17:32.000Z","build/assets/css/iCheck/line/aero.css":"2015-03-20T08:17:32.000Z","build/assets/css/iCheck/line/blue.css":"2015-03-20T08:17:32.000Z","build/assets/css/iCheck/line/green.css":"2015-03-20T08:17:32.000Z","build/assets/css/iCheck/line/grey.css":"2015-03-20T08:17:32.000Z","build/assets/css/iCheck/line/line.css":"2015-03-20T08:17:32.000Z","build/assets/css/iCheck/line/line.png":"2015-03-20T08:17:32.000Z","build/assets/css/iCheck/line/line@2x.png":"2015-03-20T08:17:32.000Z","build/assets/css/iCheck/line/orange.css":"2015-03-20T08:17:32.000Z","build/assets/css/iCheck/line/pink.css":"2015-03-20T08:17:32.000Z","build/assets/css/iCheck/line/purple.css":"2015-03-20T08:17:32.000Z","build/assets/css/iCheck/line/red.css":"2015-03-20T08:17:32.000Z","build/assets/css/iCheck/line/yellow.css":"2015-03-20T08:17:32.000Z","build/assets/css/iCheck/minimal/_all.css":"2015-03-20T08:17:32.000Z","build/assets/css/iCheck/minimal/aero.css":"2015-03-20T08:17:32.000Z","build/assets/css/iCheck/minimal/aero.png":"2015-03-20T08:17:32.000Z","build/assets/css/iCheck/minimal/aero@2x.png":"2015-03-20T08:17:32.000Z","build/assets/css/iCheck/minimal/blue.css":"2015-03-20T08:17:32.000Z","build/assets/css/iCheck/minimal/blue.png":"2015-03-20T08:17:32.000Z","build/assets/css/iCheck/minimal/blue@2x.png":"2015-03-20T08:17:32.000Z","build/assets/css/iCheck/minimal/green.css":"2015-03-20T08:17:32.000Z","build/assets/css/iCheck/minimal/green.png":"2015-03-20T08:17:32.000Z","build/assets/css/iCheck/minimal/green@2x.png":"2015-03-20T08:17:32.000Z","build/assets/css/iCheck/minimal/grey.css":"2015-03-20T08:17:32.000Z","build/assets/css/iCheck/minimal/grey.png":"2015-03-20T08:17:32.000Z","build/assets/css/iCheck/minimal/grey@2x.png":"2015-03-20T08:17:32.000Z","build/assets/css/iCheck/minimal/minimal.css":"2015-03-20T08:17:32.000Z","build/assets/css/iCheck/minimal/minimal.png":"2015-03-20T08:17:32.000Z","build/assets/css/iCheck/minimal/minimal@2x.png":"2015-03-20T08:17:32.000Z","build/assets/css/iCheck/minimal/orange.css":"2015-03-20T08:17:32.000Z","build/assets/css/iCheck/minimal/orange.png":"2015-03-20T08:17:32.000Z","build/assets/css/iCheck/minimal/orange@2x.png":"2015-03-20T08:17:32.000Z","build/assets/css/iCheck/minimal/pink.css":"2015-03-20T08:17:32.000Z","build/assets/css/iCheck/minimal/pink.png":"2015-03-20T08:17:32.000Z","build/assets/css/iCheck/minimal/pink@2x.png":"2015-03-20T08:17:32.000Z","build/assets/css/iCheck/minimal/purple.css":"2015-03-20T08:17:32.000Z","build/assets/css/iCheck/minimal/purple.png":"2015-03-20T08:17:32.000Z","build/assets/css/iCheck/minimal/purple@2x.png":"2015-03-20T08:17:32.000Z","build/assets/css/iCheck/minimal/red.css":"2015-03-20T08:17:32.000Z","build/assets/css/iCheck/minimal/red.png":"2015-03-20T08:17:32.000Z","build/assets/css/iCheck/minimal/red@2x.png":"2015-03-20T08:17:32.000Z","build/assets/css/iCheck/minimal/yellow.css":"2015-03-20T08:17:32.000Z","build/assets/css/iCheck/minimal/yellow.png":"2015-03-20T08:17:32.000Z","build/assets/css/iCheck/minimal/yellow@2x.png":"2015-03-20T08:17:32.000Z","build/assets/css/iCheck/polaris/polaris.css":"2015-03-20T08:17:32.000Z","build/assets/css/iCheck/polaris/polaris.png":"2015-03-20T08:17:32.000Z","build/assets/css/iCheck/polaris/polaris@2x.png":"2015-03-20T08:17:32.000Z","build/assets/css/iCheck/square/_all.css":"2015-03-20T08:17:32.000Z","build/assets/css/iCheck/square/aero.css":"2015-03-20T08:17:32.000Z","build/assets/css/iCheck/square/aero.png":"2015-03-20T08:17:32.000Z","build/assets/css/iCheck/square/aero@2x.png":"2015-03-20T08:17:32.000Z","build/assets/css/iCheck/square/blue.css":"2015-03-20T08:17:32.000Z","build/assets/css/iCheck/square/blue.png":"2015-03-20T08:17:32.000Z","build/assets/css/iCheck/square/blue@2x.png":"2015-03-20T08:17:32.000Z","build/assets/css/iCheck/square/green.css":"2015-03-20T08:17:32.000Z","build/assets/css/iCheck/square/green.png":"2015-03-20T08:17:32.000Z","build/assets/css/iCheck/square/green@2x.png":"2015-03-20T08:17:32.000Z","build/assets/css/iCheck/square/grey.css":"2015-03-20T08:17:32.000Z","build/assets/css/iCheck/square/grey.png":"2015-03-20T08:17:32.000Z","build/assets/css/iCheck/square/grey@2x.png":"2015-03-20T08:17:32.000Z","build/assets/css/iCheck/square/orange.css":"2015-03-20T08:17:32.000Z","build/assets/css/iCheck/square/orange.png":"2015-03-20T08:17:32.000Z","build/assets/css/iCheck/square/orange@2x.png":"2015-03-20T08:17:32.000Z","build/assets/css/iCheck/square/pink.css":"2015-03-20T08:17:32.000Z","build/assets/css/iCheck/square/pink.png":"2015-03-20T08:17:32.000Z","build/assets/css/iCheck/square/pink@2x.png":"2015-03-20T08:17:32.000Z","build/assets/css/iCheck/square/purple.css":"2015-03-20T08:17:32.000Z","build/assets/css/iCheck/square/purple.png":"2015-03-20T08:17:32.000Z","build/assets/css/iCheck/square/purple@2x.png":"2015-03-20T08:17:32.000Z","build/assets/css/iCheck/square/red.css":"2015-03-20T08:17:32.000Z","build/assets/css/iCheck/square/red.png":"2015-03-20T08:17:32.000Z","build/assets/css/iCheck/square/red@2x.png":"2015-03-20T08:17:32.000Z","build/assets/css/iCheck/square/square.css":"2015-03-20T08:17:32.000Z","build/assets/css/iCheck/square/square.png":"2015-03-20T08:17:32.000Z","build/assets/css/iCheck/square/square@2x.png":"2015-03-20T08:17:32.000Z","build/assets/css/iCheck/square/yellow.css":"2015-03-20T08:17:32.000Z","build/assets/css/iCheck/square/yellow.png":"2015-03-20T08:17:32.000Z","build/assets/css/iCheck/square/yellow@2x.png":"2015-03-20T08:17:32.000Z","build/assets/css/images/animated-overlay.gif":"2015-03-20T08:17:32.000Z","build/assets/css/images/ui-bg_flat_0_aaaaaa_40x100.png":"2015-03-20T08:17:32.000Z","build/assets/css/images/ui-bg_flat_55_fbec88_40x100.png":"2015-03-20T08:17:32.000Z","build/assets/css/images/ui-bg_glass_75_d0e5f5_1x400.png":"2015-03-20T08:17:32.000Z","build/assets/css/images/ui-bg_glass_85_dfeffc_1x400.png":"2015-03-20T08:17:32.000Z","build/assets/css/images/ui-bg_glass_95_fef1ec_1x400.png":"2015-03-20T08:17:32.000Z","build/assets/css/images/ui-bg_gloss-wave_55_5c9ccc_500x100.png":"2015-03-20T08:17:32.000Z","build/assets/css/images/ui-bg_inset-hard_100_f5f8f9_1x100.png":"2015-03-20T08:17:32.000Z","build/assets/css/images/ui-bg_inset-hard_100_fcfdfd_1x100.png":"2015-03-20T08:17:32.000Z","build/assets/css/images/ui-icons_217bc0_256x240.png":"2015-03-20T08:17:32.000Z","build/assets/css/images/ui-icons_2e83ff_256x240.png":"2015-03-20T08:17:32.000Z","build/assets/css/images/ui-icons_469bdd_256x240.png":"2015-03-20T08:17:32.000Z","build/assets/css/images/ui-icons_6da8d5_256x240.png":"2015-03-20T08:17:32.000Z","build/assets/css/images/ui-icons_cd0a0a_256x240.png":"2015-03-20T08:17:32.000Z","build/assets/css/images/ui-icons_d8e7f3_256x240.png":"2015-03-20T08:17:33.000Z","build/assets/css/images/ui-icons_f9bd01_256x240.png":"2015-03-20T08:17:33.000Z","build/assets/css/ionslider/ion.rangeSlider.css":"2015-03-20T08:17:33.000Z","build/assets/css/ionslider/ion.rangeSlider.skinFlat.css":"2015-03-20T08:17:33.000Z","build/assets/css/ionslider/ion.rangeSlider.skinNice.css":"2015-03-20T08:17:33.000Z","build/assets/css/jvectormap/jquery-jvectormap-1.2.2.css":"2015-03-20T08:17:33.000Z","build/assets/css/morris/morris.css":"2015-03-20T08:17:33.000Z","build/assets/css/timepicker/bootstrap-timepicker.css":"2015-03-20T08:17:33.000Z","build/assets/css/timepicker/bootstrap-timepicker.min.css":"2015-03-20T08:17:33.000Z","build/assets/igrow/igrow.js":"2015-03-20T08:17:33.000Z","build/assets/igrow/angular/angular-core.js":"2015-03-20T08:17:33.000Z","build/assets/igrow/angular/angular-lazyload.js":"2015-03-20T08:17:33.000Z","build/assets/igrow/css/igrow.css":"2015-03-20T08:17:33.000Z","build/assets/igrow/css/igrow.plugins.css":"2015-03-20T08:17:33.000Z","build/assets/igrow/css/igrow.util.css":"2015-03-20T08:17:33.000Z","build/assets/igrow/css/plugins.css":"2015-03-20T08:17:33.000Z","build/assets/igrow/gfx/gui/checkbox-focus.svg":"2015-03-19T10:44:13.000Z","build/assets/igrow/gfx/gui/checkbox-off.svg":"2015-03-19T10:44:13.000Z","build/assets/igrow/gfx/gui/checkbox-on.svg":"2015-03-19T10:44:13.000Z","build/assets/igrow/gfx/gui/checkbox-partial.svg":"2015-03-19T10:44:13.000Z","build/assets/igrow/gfx/gui/field-error.svg":"2015-03-19T10:44:13.000Z","build/assets/igrow/gfx/gui/field-ok.svg":"2015-03-19T10:44:13.000Z","build/assets/igrow/gfx/gui/radiobutton-focus.svg":"2015-03-19T10:44:13.000Z","build/assets/igrow/gfx/gui/radiobutton-off.svg":"2015-03-19T10:44:13.000Z","build/assets/igrow/gfx/gui/radiobutton-on (1).svg":"2015-03-19T10:44:13.000Z","build/assets/igrow/gfx/gui/radiobutton-on.svg":"2015-03-19T10:44:13.000Z","build/assets/igrow/gfx/gui/select-arrow.svg":"2015-03-19T10:44:13.000Z","build/assets/igrow/gfx1/gui1/checkbox-focus.svg":"2015-03-19T10:44:13.000Z","build/assets/igrow/gfx1/gui1/checkbox-off.svg":"2015-03-19T10:44:13.000Z","build/assets/igrow/gfx1/gui1/checkbox-on.svg":"2015-03-19T10:44:13.000Z","build/assets/igrow/gfx1/gui1/checkbox-partial.svg":"2015-03-19T10:44:13.000Z","build/assets/igrow/gfx1/gui1/field-error.svg":"2015-03-19T10:44:13.000Z","build/assets/igrow/gfx1/gui1/field-ok.svg":"2015-03-19T10:44:13.000Z","build/assets/igrow/gfx1/gui1/radiobutton-focus.svg":"2015-03-19T10:44:13.000Z","build/assets/igrow/gfx1/gui1/radiobutton-off.svg":"2015-03-19T10:44:13.000Z","build/assets/igrow/gfx1/gui1/radiobutton-on (1).svg":"2015-03-19T10:44:13.000Z","build/assets/igrow/gfx1/gui1/radiobutton-on.svg":"2015-03-19T10:44:13.000Z","build/assets/igrow/gfx1/gui1/select-arrow.svg":"2015-03-19T10:44:13.000Z","build/assets/igrow/img/mdialog/check.png":"2015-03-20T08:17:33.000Z","build/assets/igrow/img/mdialog/cross.png":"2015-03-20T08:17:33.000Z","build/assets/igrow/img/mdialog/info.png":"2015-03-20T08:17:33.000Z","build/assets/igrow/img/mdialog/loading.gif":"2015-03-20T08:17:33.000Z","build/assets/igrow/img/mdialog/success.png":"2015-03-20T08:17:33.000Z","build/assets/igrow/imobile/css/animate.css":"2015-03-19T10:44:13.000Z","build/assets/igrow/imobile/css/beautiful.css":"2015-03-19T10:44:13.000Z","build/assets/igrow/imobile/css/gray.svg":"2015-03-19T10:44:13.000Z","build/assets/igrow/imobile/css/imobile.css":"2015-03-19T10:44:13.000Z","build/assets/igrow/imobile/images/arrow-down.png":"2015-03-19T10:44:13.000Z","build/assets/igrow/imobile/images/arrow-right.png":"2015-03-19T10:44:13.000Z","build/assets/igrow/imobile/images/arrow-up.png":"2015-03-19T10:44:13.000Z","build/assets/igrow/imobile/images/audio.png":"2015-03-19T10:44:13.000Z","build/assets/igrow/imobile/images/avatar-80.png":"2015-03-19T10:44:13.000Z","build/assets/igrow/imobile/images/base_z2254d3.png":"2015-03-19T10:44:13.000Z","build/assets/igrow/imobile/images/icon67_status.png":"2015-03-19T10:44:13.000Z","build/assets/igrow/imobile/images/icon80_smile.png":"2015-03-19T10:44:13.000Z","build/assets/igrow/imobile/images/img-error.jpg":"2015-03-19T10:44:13.000Z","build/assets/igrow/imobile/images/landscape-bg.png":"2015-03-19T10:44:13.000Z","build/assets/igrow/imobile/images/landscape-phone.png":"2015-03-19T10:44:13.000Z","build/assets/igrow/imobile/images/loading-32.gif":"2015-03-19T10:44:13.000Z","build/assets/igrow/imobile/images/loading.gif":"2015-03-19T10:44:13.000Z","build/assets/igrow/imobile/images/no-cover-135.jpg":"2015-03-19T10:44:13.000Z","build/assets/igrow/imobile/images/photo-selected.png":"2015-03-19T10:44:13.000Z","build/assets/igrow/imobile/images/select-arrow.svg":"2015-03-19T10:44:13.000Z","build/assets/igrow/imobile/images/share-bg.png":"2015-03-19T10:44:13.000Z","build/assets/igrow/imobile/images/success.png":"2015-03-19T10:44:13.000Z","build/assets/igrow/imobile/images/units-icons.png":"2015-03-19T10:44:13.000Z","build/assets/igrow/imobile/images/video.png":"2015-03-19T10:44:13.000Z","build/assets/igrow/imobile/images/分享.png":"2015-03-19T10:44:13.000Z","build/assets/igrow/imobile/js/imobile.js":"2015-03-19T10:44:13.000Z","build/assets/igrow/imobile/js/zMobile.js":"2015-03-19T10:44:13.000Z","build/assets/igrow/imobile/js/widgets/load.js":"2015-03-19T10:44:13.000Z","build/assets/igrow/public/igrow.util.js":"2015-03-19T10:44:13.000Z","build/assets/igrow/public/sizzle.js":"2015-03-19T10:44:13.000Z","build/assets/igrow/public/utils.js":"2015-03-19T10:44:13.000Z","build/assets/igrow/qaq/css/qaq.css":"2015-03-19T10:44:13.000Z","build/assets/igrow/qaq/images/loading-32.gif":"2015-03-19T10:44:13.000Z","build/assets/igrow/qaq/images/message-icon.png":"2015-03-19T10:44:13.000Z","build/assets/igrow/qaq/images/sb_loading.gif":"2015-03-19T10:44:13.000Z","build/assets/igrow/qaq/js/qaq.js":"2015-03-19T10:44:13.000Z","build/assets/igrow/test/index.html":"2015-03-20T08:17:33.000Z","build/assets/igrow/test/images/1.jpg":"2015-03-20T08:17:33.000Z","build/assets/img/ajax-loader.gif":"2015-03-20T08:17:33.000Z","build/assets/img/ajax-loader1.gif":"2015-03-20T08:17:33.000Z","build/assets/img/avatar.png":"2015-03-20T08:17:33.000Z","build/assets/img/avatar04.png":"2015-03-20T08:17:33.000Z","build/assets/img/avatar2.png":"2015-03-20T08:17:33.000Z","build/assets/img/avatar3.png":"2015-03-20T08:17:33.000Z","build/assets/img/avatar5.png":"2015-03-20T08:17:33.000Z","build/assets/img/blur-background04.jpg":"2015-03-20T08:17:33.000Z","build/assets/img/blur-background08.jpg":"2015-03-20T08:17:33.000Z","build/assets/img/blur-background09.jpg":"2015-03-20T08:17:33.000Z","build/assets/img/cat.jpg":"2015-03-20T08:17:33.000Z","build/assets/img/datePicker.gif":"2015-03-20T08:17:33.000Z","build/assets/img/dateicon.png":"2015-03-20T08:17:33.000Z","build/assets/img/icons.png":"2015-03-20T08:17:33.000Z","build/assets/img/lock-avatar.jpg":"2015-03-20T08:17:33.000Z","build/assets/img/sprite-skin-flat.png":"2015-03-20T08:17:33.000Z","build/assets/img/sprite-skin-nice.png":"2015-03-20T08:17:33.000Z","build/assets/img/user-bg.png":"2015-03-20T08:17:33.000Z","build/assets/img/user.jpg":"2015-03-20T08:17:33.000Z","build/assets/img/user2.jpg":"2015-03-20T08:17:33.000Z","build/assets/img/avatar/1.jpg":"2015-03-20T08:17:33.000Z","build/assets/img/avatar/10.jpg":"2015-03-20T08:17:33.000Z","build/assets/img/avatar/2.jpg":"2015-03-20T08:17:33.000Z","build/assets/img/avatar/3.jpg":"2015-03-20T08:17:33.000Z","build/assets/img/avatar/4.jpg":"2015-03-20T08:17:33.000Z","build/assets/img/avatar/5.jpg":"2015-03-20T08:17:33.000Z","build/assets/img/avatar/6.jpg":"2015-03-20T08:17:33.000Z","build/assets/img/avatar/7.jpg":"2015-03-20T08:17:33.000Z","build/assets/img/avatar/8.jpg":"2015-03-20T08:17:33.000Z","build/assets/img/avatar/9.jpg":"2015-03-20T08:17:33.000Z","build/assets/img/bootstrap-colorpicker/alpha-horizontal.png":"2015-03-20T08:17:33.000Z","build/assets/img/bootstrap-colorpicker/alpha.png":"2015-03-20T08:17:33.000Z","build/assets/img/bootstrap-colorpicker/hue-horizontal.png":"2015-03-20T08:17:33.000Z","build/assets/img/bootstrap-colorpicker/hue.png":"2015-03-20T08:17:33.000Z","build/assets/img/bootstrap-colorpicker/saturation.png":"2015-03-20T08:17:33.000Z","build/assets/img/credit/american-express.png":"2015-03-20T08:17:33.000Z","build/assets/img/credit/cirrus.png":"2015-03-20T08:17:33.000Z","build/assets/img/credit/mastercard.png":"2015-03-20T08:17:33.000Z","build/assets/img/credit/mestro.png":"2015-03-20T08:17:33.000Z","build/assets/img/credit/paypal.png":"2015-03-20T08:17:33.000Z","build/assets/img/credit/paypal2.png":"2015-03-20T08:17:33.000Z","build/assets/img/credit/visa.png":"2015-03-20T08:17:33.000Z","build/assets/img/login/bg.jpg":"2015-03-20T08:17:33.000Z","build/assets/img/login/form_bg.png":"2015-03-20T08:17:33.000Z","build/assets/img/login/icons.png":"2015-03-20T08:17:33.000Z","build/assets/img/login/text-boxes.png":"2015-03-20T08:17:33.000Z","build/assets/img/public/404.jpg":"2015-03-20T08:17:33.000Z","build/assets/img/public/audio.png":"2015-03-20T08:17:33.000Z","build/assets/img/public/avatar-80.png":"2015-03-20T08:17:33.000Z","build/assets/img/public/img-error.jpg":"2015-03-20T08:17:33.000Z","build/assets/img/public/loading-20.gif":"2015-03-20T08:17:33.000Z","build/assets/img/public/loading-32.gif":"2015-03-20T08:17:33.000Z","build/assets/img/public/no-cover-135.jpg":"2015-03-20T08:17:33.000Z","build/assets/img/public/photo-selected.png":"2015-03-20T08:17:33.000Z","build/assets/img/public/video.png":"2015-03-20T08:17:33.000Z","build/assets/img/public/welcome.jpg":"2015-03-20T08:17:33.000Z","build/assets/js/untitled.js":"2015-03-20T08:17:34.000Z","build/assets/js/AdminLTE/adminApp.js":"2015-03-20T08:17:33.000Z","build/assets/js/AdminLTE/api.js":"2015-03-20T08:17:33.000Z","build/assets/js/AdminLTE/app.js":"2015-03-20T08:17:33.000Z","build/assets/js/AdminLTE/dashboard.js":"2015-03-20T08:17:33.000Z","build/assets/js/AdminLTE/demo.js":"2015-03-20T08:17:33.000Z","build/assets/js/AdminLTE/guests.js":"2015-03-20T08:17:33.000Z","build/assets/js/AdminLTE/igrow.js":"2015-03-20T08:17:33.000Z","build/assets/js/AdminLTE/ueditor.config.js":"2015-03-20T08:17:33.000Z","build/assets/js/controllers/article/article.html":"2015-03-20T08:17:33.000Z","build/assets/js/controllers/article/articleController.js":"2015-03-20T08:17:33.000Z","build/assets/js/controllers/article/articleEdit.html":"2015-03-20T08:17:33.000Z","build/assets/js/controllers/article/articleEditController.js":"2015-03-20T08:17:33.000Z","build/assets/js/controllers/article/articlePreview.html":"2015-03-20T08:17:33.000Z","build/assets/js/controllers/article/articlePreviewController.js":"2015-03-20T08:17:33.000Z","build/assets/js/controllers/article/articleType.html":"2015-03-20T08:17:33.000Z","build/assets/js/controllers/article/articleTypeController.js":"2015-03-20T08:17:33.000Z","build/assets/js/controllers/article/articleTypeEdit.html":"2015-03-20T08:17:33.000Z","build/assets/js/controllers/dashboard/dashboard.html":"2015-03-20T08:17:33.000Z","build/assets/js/controllers/user/user.html":"2015-03-20T08:17:33.000Z","build/assets/js/controllers/user/userController.js":"2015-03-20T08:17:33.000Z","build/assets/js/controllers/user/userEdit.html":"2015-03-20T08:17:33.000Z","build/assets/js/plugins/bootstrap-slider/bootstrap-slider.js":"2015-03-20T08:17:33.000Z","build/assets/js/plugins/bootstrap-wysihtml5/bootstrap3-wysihtml5.all.min.js":"2015-03-20T08:17:33.000Z","build/assets/js/plugins/bootstrap-wysihtml5/bootstrap3-wysihtml5.js":"2015-03-20T08:17:33.000Z","build/assets/js/plugins/colorpicker/bootstrap-colorpicker.js":"2015-03-20T08:17:33.000Z","build/assets/js/plugins/colorpicker/bootstrap-colorpicker.min.js":"2015-03-20T08:17:33.000Z","build/assets/js/plugins/datatables/dataTables.bootstrap.js":"2015-03-20T08:17:33.000Z","build/assets/js/plugins/datatables/jquery.dataTables.js":"2015-03-20T08:17:33.000Z","build/assets/js/plugins/datepicker/bootstrap-datepicker.js":"2015-03-20T08:17:33.000Z","build/assets/js/plugins/datepicker/locales/bootstrap-datepicker.ar.js":"2015-03-20T08:17:33.000Z","build/assets/js/plugins/datepicker/locales/bootstrap-datepicker.az.js":"2015-03-20T08:17:33.000Z","build/assets/js/plugins/datepicker/locales/bootstrap-datepicker.bg.js":"2015-03-20T08:17:33.000Z","build/assets/js/plugins/datepicker/locales/bootstrap-datepicker.ca.js":"2015-03-20T08:17:33.000Z","build/assets/js/plugins/datepicker/locales/bootstrap-datepicker.cs.js":"2015-03-20T08:17:33.000Z","build/assets/js/plugins/datepicker/locales/bootstrap-datepicker.cy.js":"2015-03-20T08:17:33.000Z","build/assets/js/plugins/datepicker/locales/bootstrap-datepicker.da.js":"2015-03-20T08:17:33.000Z","build/assets/js/plugins/datepicker/locales/bootstrap-datepicker.de.js":"2015-03-20T08:17:33.000Z","build/assets/js/plugins/datepicker/locales/bootstrap-datepicker.el.js":"2015-03-20T08:17:33.000Z","build/assets/js/plugins/datepicker/locales/bootstrap-datepicker.es.js":"2015-03-20T08:17:33.000Z","build/assets/js/plugins/datepicker/locales/bootstrap-datepicker.et.js":"2015-03-20T08:17:33.000Z","build/assets/js/plugins/datepicker/locales/bootstrap-datepicker.fa.js":"2015-03-20T08:17:33.000Z","build/assets/js/plugins/datepicker/locales/bootstrap-datepicker.fi.js":"2015-03-20T08:17:33.000Z","build/assets/js/plugins/datepicker/locales/bootstrap-datepicker.fr.js":"2015-03-20T08:17:33.000Z","build/assets/js/plugins/datepicker/locales/bootstrap-datepicker.gl.js":"2015-03-20T08:17:33.000Z","build/assets/js/plugins/datepicker/locales/bootstrap-datepicker.he.js":"2015-03-20T08:17:33.000Z","build/assets/js/plugins/datepicker/locales/bootstrap-datepicker.hr.js":"2015-03-20T08:17:33.000Z","build/assets/js/plugins/datepicker/locales/bootstrap-datepicker.hu.js":"2015-03-20T08:17:33.000Z","build/assets/js/plugins/datepicker/locales/bootstrap-datepicker.id.js":"2015-03-20T08:17:33.000Z","build/assets/js/plugins/datepicker/locales/bootstrap-datepicker.is.js":"2015-03-20T08:17:33.000Z","build/assets/js/plugins/datepicker/locales/bootstrap-datepicker.it.js":"2015-03-20T08:17:33.000Z","build/assets/js/plugins/datepicker/locales/bootstrap-datepicker.ja.js":"2015-03-20T08:17:33.000Z","build/assets/js/plugins/datepicker/locales/bootstrap-datepicker.ka.js":"2015-03-20T08:17:33.000Z","build/assets/js/plugins/datepicker/locales/bootstrap-datepicker.kk.js":"2015-03-20T08:17:33.000Z","build/assets/js/plugins/datepicker/locales/bootstrap-datepicker.kr.js":"2015-03-20T08:17:33.000Z","build/assets/js/plugins/datepicker/locales/bootstrap-datepicker.lt.js":"2015-03-20T08:17:33.000Z","build/assets/js/plugins/datepicker/locales/bootstrap-datepicker.lv.js":"2015-03-20T08:17:33.000Z","build/assets/js/plugins/datepicker/locales/bootstrap-datepicker.mk.js":"2015-03-20T08:17:33.000Z","build/assets/js/plugins/datepicker/locales/bootstrap-datepicker.ms.js":"2015-03-20T08:17:33.000Z","build/assets/js/plugins/datepicker/locales/bootstrap-datepicker.nb.js":"2015-03-20T08:17:33.000Z","build/assets/js/plugins/datepicker/locales/bootstrap-datepicker.nl-BE.js":"2015-03-20T08:17:33.000Z","build/assets/js/plugins/datepicker/locales/bootstrap-datepicker.nl.js":"2015-03-20T08:17:33.000Z","build/assets/js/plugins/datepicker/locales/bootstrap-datepicker.no.js":"2015-03-20T08:17:33.000Z","build/assets/js/plugins/datepicker/locales/bootstrap-datepicker.pl.js":"2015-03-20T08:17:33.000Z","build/assets/js/plugins/datepicker/locales/bootstrap-datepicker.pt-BR.js":"2015-03-20T08:17:33.000Z","build/assets/js/plugins/datepicker/locales/bootstrap-datepicker.pt.js":"2015-03-20T08:17:33.000Z","build/assets/js/plugins/datepicker/locales/bootstrap-datepicker.ro.js":"2015-03-20T08:17:33.000Z","build/assets/js/plugins/datepicker/locales/bootstrap-datepicker.rs-latin.js":"2015-03-20T08:17:33.000Z","build/assets/js/plugins/datepicker/locales/bootstrap-datepicker.rs.js":"2015-03-20T08:17:33.000Z","build/assets/js/plugins/datepicker/locales/bootstrap-datepicker.ru.js":"2015-03-20T08:17:33.000Z","build/assets/js/plugins/datepicker/locales/bootstrap-datepicker.sk.js":"2015-03-20T08:17:33.000Z","build/assets/js/plugins/datepicker/locales/bootstrap-datepicker.sl.js":"2015-03-20T08:17:33.000Z","build/assets/js/plugins/datepicker/locales/bootstrap-datepicker.sq.js":"2015-03-20T08:17:33.000Z","build/assets/js/plugins/datepicker/locales/bootstrap-datepicker.sv.js":"2015-03-20T08:17:33.000Z","build/assets/js/plugins/datepicker/locales/bootstrap-datepicker.sw.js":"2015-03-20T08:17:33.000Z","build/assets/js/plugins/datepicker/locales/bootstrap-datepicker.th.js":"2015-03-20T08:17:33.000Z","build/assets/js/plugins/datepicker/locales/bootstrap-datepicker.tr.js":"2015-03-20T08:17:33.000Z","build/assets/js/plugins/datepicker/locales/bootstrap-datepicker.ua.js":"2015-03-20T08:17:33.000Z","build/assets/js/plugins/datepicker/locales/bootstrap-datepicker.vi.js":"2015-03-20T08:17:33.000Z","build/assets/js/plugins/datepicker/locales/bootstrap-datepicker.zh-CN.js":"2015-03-20T08:17:33.000Z","build/assets/js/plugins/datepicker/locales/bootstrap-datepicker.zh-TW.js":"2015-03-20T08:17:33.000Z","build/assets/js/plugins/daterangepicker/daterangepicker.js":"2015-03-20T08:17:33.000Z","build/assets/js/plugins/flot/excanvas.js":"2015-03-20T08:17:33.000Z","build/assets/js/plugins/flot/excanvas.min.js":"2015-03-20T08:17:33.000Z","build/assets/js/plugins/flot/jquery.colorhelpers.js":"2015-03-20T08:17:33.000Z","build/assets/js/plugins/flot/jquery.colorhelpers.min.js":"2015-03-20T08:17:33.000Z","build/assets/js/plugins/flot/jquery.flot.canvas.js":"2015-03-20T08:17:33.000Z","build/assets/js/plugins/flot/jquery.flot.canvas.min.js":"2015-03-20T08:17:33.000Z","build/assets/js/plugins/flot/jquery.flot.categories.js":"2015-03-20T08:17:33.000Z","build/assets/js/plugins/flot/jquery.flot.categories.min.js":"2015-03-20T08:17:33.000Z","build/assets/js/plugins/flot/jquery.flot.crosshair.js":"2015-03-20T08:17:33.000Z","build/assets/js/plugins/flot/jquery.flot.crosshair.min.js":"2015-03-20T08:17:33.000Z","build/assets/js/plugins/flot/jquery.flot.errorbars.js":"2015-03-20T08:17:33.000Z","build/assets/js/plugins/flot/jquery.flot.errorbars.min.js":"2015-03-20T08:17:33.000Z","build/assets/js/plugins/flot/jquery.flot.fillbetween.js":"2015-03-20T08:17:33.000Z","build/assets/js/plugins/flot/jquery.flot.fillbetween.min.js":"2015-03-20T08:17:33.000Z","build/assets/js/plugins/flot/jquery.flot.image.js":"2015-03-20T08:17:33.000Z","build/assets/js/plugins/flot/jquery.flot.image.min.js":"2015-03-20T08:17:33.000Z","build/assets/js/plugins/flot/jquery.flot.js":"2015-03-20T08:17:33.000Z","build/assets/js/plugins/flot/jquery.flot.min.js":"2015-03-20T08:17:33.000Z","build/assets/js/plugins/flot/jquery.flot.navigate.js":"2015-03-20T08:17:33.000Z","build/assets/js/plugins/flot/jquery.flot.navigate.min.js":"2015-03-20T08:17:33.000Z","build/assets/js/plugins/flot/jquery.flot.pie.js":"2015-03-20T08:17:33.000Z","build/assets/js/plugins/flot/jquery.flot.pie.min.js":"2015-03-20T08:17:33.000Z","build/assets/js/plugins/flot/jquery.flot.resize.js":"2015-03-20T08:17:33.000Z","build/assets/js/plugins/flot/jquery.flot.resize.min.js":"2015-03-20T08:17:33.000Z","build/assets/js/plugins/flot/jquery.flot.selection.js":"2015-03-20T08:17:33.000Z","build/assets/js/plugins/flot/jquery.flot.selection.min.js":"2015-03-20T08:17:33.000Z","build/assets/js/plugins/flot/jquery.flot.stack.js":"2015-03-20T08:17:33.000Z","build/assets/js/plugins/flot/jquery.flot.stack.min.js":"2015-03-20T08:17:33.000Z","build/assets/js/plugins/flot/jquery.flot.symbol.js":"2015-03-20T08:17:33.000Z","build/assets/js/plugins/flot/jquery.flot.symbol.min.js":"2015-03-20T08:17:33.000Z","build/assets/js/plugins/flot/jquery.flot.threshold.js":"2015-03-20T08:17:33.000Z","build/assets/js/plugins/flot/jquery.flot.threshold.min.js":"2015-03-20T08:17:33.000Z","build/assets/js/plugins/flot/jquery.flot.time.js":"2015-03-20T08:17:33.000Z","build/assets/js/plugins/flot/jquery.flot.time.min.js":"2015-03-20T08:17:33.000Z","build/assets/js/plugins/iCheck/icheck.js":"2015-03-20T08:17:33.000Z","build/assets/js/plugins/iCheck/icheck.min.js":"2015-03-20T08:17:33.000Z","build/assets/js/plugins/input-mask/jquery.inputmask.date.extensions.js":"2015-03-20T08:17:33.000Z","build/assets/js/plugins/input-mask/jquery.inputmask.extensions.js":"2015-03-20T08:17:34.000Z","build/assets/js/plugins/input-mask/jquery.inputmask.js":"2015-03-20T08:17:34.000Z","build/assets/js/plugins/input-mask/jquery.inputmask.numeric.extensions.js":"2015-03-20T08:17:34.000Z","build/assets/js/plugins/input-mask/jquery.inputmask.phone.extensions.js":"2015-03-20T08:17:34.000Z","build/assets/js/plugins/input-mask/jquery.inputmask.regex.extensions.js":"2015-03-20T08:17:34.000Z","build/assets/js/plugins/input-mask/phone-codes/phone-be.json":"2015-03-20T08:17:34.000Z","build/assets/js/plugins/input-mask/phone-codes/phone-codes.json":"2015-03-20T08:17:34.000Z","build/assets/js/plugins/input-mask/phone-codes/readme.txt":"2015-03-20T08:17:34.000Z","build/assets/js/plugins/ionslider/ion.rangeSlider.min.js":"2015-03-20T08:17:34.000Z","build/assets/js/plugins/jqueryKnob/jquery.knob.js":"2015-03-20T08:17:34.000Z","build/assets/js/plugins/jvectormap/jquery-jvectormap-1.2.2.min.js":"2015-03-20T08:17:34.000Z","build/assets/js/plugins/jvectormap/jquery-jvectormap-world-mill-en.js":"2015-03-20T08:17:34.000Z","build/assets/js/plugins/misc/html5shiv.js":"2015-03-20T08:17:34.000Z","build/assets/js/plugins/misc/jquery.ba-resize.min.js":"2015-03-20T08:17:34.000Z","build/assets/js/plugins/misc/jquery.placeholder.js":"2015-03-20T08:17:34.000Z","build/assets/js/plugins/misc/modernizr.min.js":"2015-03-20T08:17:34.000Z","build/assets/js/plugins/misc/respond.min.js":"2015-03-20T08:17:34.000Z","build/assets/js/plugins/morris/morris.js":"2015-03-20T08:17:34.000Z","build/assets/js/plugins/morris/morris.min.js":"2015-03-20T08:17:34.000Z","build/assets/js/plugins/slimScroll/jquery.slimscroll.js":"2015-03-20T08:17:34.000Z","build/assets/js/plugins/slimScroll/jquery.slimscroll.min.js":"2015-03-20T08:17:34.000Z","build/assets/js/plugins/slimScroll/slimScroll.jquery.json":"2015-03-20T08:17:34.000Z","build/assets/js/plugins/sparkline/jquery.sparkline.js":"2015-03-20T08:17:34.000Z","build/assets/js/plugins/sparkline/jquery.sparkline.min.js":"2015-03-20T08:17:34.000Z","build/assets/js/plugins/timepicker/bootstrap-timepicker.js":"2015-03-20T08:17:34.000Z","build/assets/js/plugins/timepicker/bootstrap-timepicker.min.js":"2015-03-20T08:17:34.000Z","build/assets/js/public/injectorApp.js":"2015-03-20T08:17:34.000Z","build/assets/js/public/media.js":"2015-03-20T08:17:34.000Z","build/assets/plugins/jquery.cookie.js":"2015-03-20T08:17:34.000Z","build/assets/plugins/jquery.form.js":"2015-03-20T08:17:34.000Z","build/assets/plugins/placeholder.js":"2015-03-20T08:17:34.000Z","build/assets/plugins/progress.js":"2015-03-20T08:17:34.000Z","build/assets/plugins/vx-modal.js":"2015-03-20T08:17:34.000Z","build/assets/plugins/zh-hans_i5XX0Sq-0hHkPz0Nznhb_bUUp3Xjwx01qj3MJG8pPSE.js":"2015-03-20T08:17:34.000Z","build/assets/plugins/geo/demo.html":"2015-03-20T08:17:34.000Z","build/assets/plugins/geo/geo.js":"2015-03-20T08:17:34.000Z","build/assets/plugins/lazyload/jquery.lazyload.js":"2015-03-20T08:17:34.000Z","build/assets/plugins/lazyload/jquery.lazyload.min.js":"2015-03-20T08:17:34.000Z","build/assets/plugins/lazyload/img/grey.gif":"2015-03-20T08:17:34.000Z","build/assets/plugins/lazyload/img/transparent.gif":"2015-03-20T08:17:34.000Z","build/assets/plugins/lazyload/img/white.gif":"2015-03-20T08:17:34.000Z","build/assets/tpl/404.html":"2015-03-20T08:17:34.000Z","build/assets/vendor/My97DatePicker/WdatePicker.js":"2015-03-20T08:17:34.000Z","build/assets/vendor/My97DatePicker/calendar.js":"2015-03-20T08:17:34.000Z","build/assets/vendor/My97DatePicker/lang/en.js":"2015-03-20T08:17:34.000Z","build/assets/vendor/My97DatePicker/lang/zh-cn.js":"2015-03-20T08:17:34.000Z","build/assets/vendor/My97DatePicker/lang/zh-tw.js":"2015-03-20T08:17:34.000Z","build/assets/vendor/My97DatePicker/skin/WdatePicker.css":"2015-03-20T08:17:34.000Z","build/assets/vendor/My97DatePicker/skin/datePicker.gif":"2015-03-20T08:17:34.000Z","build/assets/vendor/My97DatePicker/skin/default/datepicker.css":"2015-03-20T08:17:34.000Z","build/assets/vendor/My97DatePicker/skin/default/img.gif":"2015-03-20T08:17:34.000Z","build/assets/vendor/My97DatePicker/skin/whyGreen/bg.jpg":"2015-03-20T08:17:34.000Z","build/assets/vendor/My97DatePicker/skin/whyGreen/datepicker.css":"2015-03-20T08:17:34.000Z","build/assets/vendor/My97DatePicker/skin/whyGreen/img.gif":"2015-03-20T08:17:34.000Z","build/assets/vendor/angularjs/1.2.14/angular-animate.js":"2015-03-20T08:17:34.000Z","build/assets/vendor/angularjs/1.2.14/angular-animate.min.js":"2015-03-20T08:17:34.000Z","build/assets/vendor/angularjs/1.2.14/angular-animate.min.js.map":"2015-03-20T08:17:34.000Z","build/assets/vendor/angularjs/1.2.14/angular-cookies.js":"2015-03-20T08:17:34.000Z","build/assets/vendor/angularjs/1.2.14/angular-cookies.min.js":"2015-03-20T08:17:34.000Z","build/assets/vendor/angularjs/1.2.14/angular-cookies.min.js.map":"2015-03-20T08:17:34.000Z","build/assets/vendor/angularjs/1.2.14/angular-csp.css":"2015-03-20T08:17:34.000Z","build/assets/vendor/angularjs/1.2.14/angular-loader.js":"2015-03-20T08:17:34.000Z","build/assets/vendor/angularjs/1.2.14/angular-loader.min.js":"2015-03-20T08:17:34.000Z","build/assets/vendor/angularjs/1.2.14/angular-loader.min.js.map":"2015-03-20T08:17:34.000Z","build/assets/vendor/angularjs/1.2.14/angular-mocks.js":"2015-03-20T08:17:34.000Z","build/assets/vendor/angularjs/1.2.14/angular-resource.js":"2015-03-20T08:17:34.000Z","build/assets/vendor/angularjs/1.2.14/angular-resource.min.js":"2015-03-20T08:17:34.000Z","build/assets/vendor/angularjs/1.2.14/angular-resource.min.js.map":"2015-03-20T08:17:34.000Z","build/assets/vendor/angularjs/1.2.14/angular-route.js":"2015-03-20T08:17:34.000Z","build/assets/vendor/angularjs/1.2.14/angular-route.min.js":"2015-03-20T08:17:34.000Z","build/assets/vendor/angularjs/1.2.14/angular-route.min.js.map":"2015-03-20T08:17:34.000Z","build/assets/vendor/angularjs/1.2.14/angular-sanitize.js":"2015-03-20T08:17:34.000Z","build/assets/vendor/angularjs/1.2.14/angular-sanitize.min.js":"2015-03-20T08:17:34.000Z","build/assets/vendor/angularjs/1.2.14/angular-sanitize.min.js.map":"2015-03-20T08:17:34.000Z","build/assets/vendor/angularjs/1.2.14/angular-scenario.js":"2015-03-20T08:17:34.000Z","build/assets/vendor/angularjs/1.2.14/angular-touch.js":"2015-03-20T08:17:34.000Z","build/assets/vendor/angularjs/1.2.14/angular-touch.min.js":"2015-03-20T08:17:34.000Z","build/assets/vendor/angularjs/1.2.14/angular-touch.min.js.map":"2015-03-20T08:17:34.000Z","build/assets/vendor/angularjs/1.2.14/angular.js":"2015-03-20T08:17:34.000Z","build/assets/vendor/angularjs/1.2.14/angular.min.js":"2015-03-20T08:17:34.000Z","build/assets/vendor/angularjs/1.2.14/angular.min.js.map":"2015-03-20T08:17:34.000Z","build/assets/vendor/angularjs/1.2.14/errors.json":"2015-03-20T08:17:34.000Z","build/assets/vendor/angularjs/1.2.14/version.json":"2015-03-20T08:17:34.000Z","build/assets/vendor/angularjs/1.2.14/version.txt":"2015-03-20T08:17:34.000Z","build/assets/vendor/bootstrap/3.0.0/css/bootstrap-theme.css":"2015-03-20T08:17:34.000Z","build/assets/vendor/bootstrap/3.0.0/css/bootstrap-theme.css.map":"2015-03-20T08:17:34.000Z","build/assets/vendor/bootstrap/3.0.0/css/bootstrap-theme.min.css":"2015-03-20T08:17:34.000Z","build/assets/vendor/bootstrap/3.0.0/css/bootstrap.css":"2015-03-20T08:17:34.000Z","build/assets/vendor/bootstrap/3.0.0/css/bootstrap.css.map":"2015-03-20T08:17:34.000Z","build/assets/vendor/bootstrap/3.0.0/css/bootstrap.min.css":"2015-03-20T08:17:34.000Z","build/assets/vendor/bootstrap/3.0.0/fonts/glyphicons-halflings-regular.eot":"2015-03-20T08:17:34.000Z","build/assets/vendor/bootstrap/3.0.0/fonts/glyphicons-halflings-regular.svg":"2015-03-20T08:17:34.000Z","build/assets/vendor/bootstrap/3.0.0/fonts/glyphicons-halflings-regular.ttf":"2015-03-20T08:17:34.000Z","build/assets/vendor/bootstrap/3.0.0/fonts/glyphicons-halflings-regular.woff":"2015-03-20T08:17:34.000Z","build/assets/vendor/bootstrap/3.0.0/js/bootstrap.js":"2015-03-20T08:17:34.000Z","build/assets/vendor/bootstrap/3.0.0/js/bootstrap.min.js":"2015-03-20T08:17:34.000Z","build/assets/vendor/bootstrap/3.0.0/js/npm.js":"2015-03-20T08:17:34.000Z","build/assets/vendor/font-awesome/4.2.0/css/font-awesome.css":"2015-03-20T08:17:34.000Z","build/assets/vendor/font-awesome/4.2.0/css/font-awesome.min.css":"2015-03-20T08:17:34.000Z","build/assets/vendor/font-awesome/4.2.0/fonts/FontAwesome.otf":"2015-03-20T08:17:34.000Z","build/assets/vendor/font-awesome/4.2.0/fonts/fontawesome-webfont.eot":"2015-03-20T08:17:34.000Z","build/assets/vendor/font-awesome/4.2.0/fonts/fontawesome-webfont.svg":"2015-03-20T08:17:34.000Z","build/assets/vendor/font-awesome/4.2.0/fonts/fontawesome-webfont.ttf":"2015-03-20T08:17:34.000Z","build/assets/vendor/font-awesome/4.2.0/fonts/fontawesome-webfont.woff":"2015-03-20T08:17:34.000Z","build/assets/vendor/font-awesome/4.2.0/less/bordered-pulled.less":"2015-03-20T08:17:34.000Z","build/assets/vendor/font-awesome/4.2.0/less/core.less":"2015-03-20T08:17:34.000Z","build/assets/vendor/font-awesome/4.2.0/less/fixed-width.less":"2015-03-20T08:17:34.000Z","build/assets/vendor/font-awesome/4.2.0/less/font-awesome.less":"2015-03-20T08:17:34.000Z","build/assets/vendor/font-awesome/4.2.0/less/icons.less":"2015-03-20T08:17:34.000Z","build/assets/vendor/font-awesome/4.2.0/less/larger.less":"2015-03-20T08:17:34.000Z","build/assets/vendor/font-awesome/4.2.0/less/list.less":"2015-03-20T08:17:34.000Z","build/assets/vendor/font-awesome/4.2.0/less/mixins.less":"2015-03-20T08:17:34.000Z","build/assets/vendor/font-awesome/4.2.0/less/path.less":"2015-03-20T08:17:34.000Z","build/assets/vendor/font-awesome/4.2.0/less/rotated-flipped.less":"2015-03-20T08:17:34.000Z","build/assets/vendor/font-awesome/4.2.0/less/spinning.less":"2015-03-20T08:17:34.000Z","build/assets/vendor/font-awesome/4.2.0/less/stacked.less":"2015-03-20T08:17:34.000Z","build/assets/vendor/font-awesome/4.2.0/less/variables.less":"2015-03-20T08:17:34.000Z","build/assets/vendor/font-awesome/4.2.0/scss/_bordered-pulled.scss":"2015-03-20T08:17:34.000Z","build/assets/vendor/font-awesome/4.2.0/scss/_core.scss":"2015-03-20T08:17:34.000Z","build/assets/vendor/font-awesome/4.2.0/scss/_fixed-width.scss":"2015-03-20T08:17:34.000Z","build/assets/vendor/font-awesome/4.2.0/scss/_icons.scss":"2015-03-20T08:17:34.000Z","build/assets/vendor/font-awesome/4.2.0/scss/_larger.scss":"2015-03-20T08:17:34.000Z","build/assets/vendor/font-awesome/4.2.0/scss/_list.scss":"2015-03-20T08:17:34.000Z","build/assets/vendor/font-awesome/4.2.0/scss/_mixins.scss":"2015-03-20T08:17:34.000Z","build/assets/vendor/font-awesome/4.2.0/scss/_path.scss":"2015-03-20T08:17:34.000Z","build/assets/vendor/font-awesome/4.2.0/scss/_rotated-flipped.scss":"2015-03-20T08:17:34.000Z","build/assets/vendor/font-awesome/4.2.0/scss/_spinning.scss":"2015-03-20T08:17:34.000Z","build/assets/vendor/font-awesome/4.2.0/scss/_stacked.scss":"2015-03-20T08:17:34.000Z","build/assets/vendor/font-awesome/4.2.0/scss/_variables.scss":"2015-03-20T08:17:34.000Z","build/assets/vendor/font-awesome/4.2.0/scss/font-awesome.scss":"2015-03-20T08:17:34.000Z","build/assets/vendor/iscroll/iscroll-4.2.5.js":"2015-03-20T08:17:34.000Z","build/assets/vendor/jquery/1.11.1/jquery.min.js":"2015-03-20T08:17:34.000Z","build/assets/vendor/jquery/1.8.3/jquery.js":"2015-03-20T08:17:34.000Z","build/assets/vendor/jquery/1.8.3/jquery.min.js":"2015-03-20T08:17:34.000Z","build/assets/vendor/mediaelement/2.13.1/bigplay.svg":"2015-03-20T08:17:34.000Z","build/assets/vendor/mediaelement/2.13.1/controls.svg":"2015-03-20T08:17:34.000Z","build/assets/vendor/mediaelement/2.13.1/loading.gif":"2015-03-20T08:17:34.000Z","build/assets/vendor/mediaelement/2.13.1/mediaelement-and-player.min.js":"2015-03-20T08:17:34.000Z","build/assets/vendor/mediaelement/2.13.1/mediaelementplayer.min.css":"2015-03-20T08:17:34.000Z","build/assets/vendor/seajs/2.0.0/plugin-combo.js":"2015-03-20T08:17:34.000Z","build/assets/vendor/seajs/2.0.0/plugin-debug.js":"2015-03-20T08:17:34.000Z","build/assets/vendor/seajs/2.0.0/plugin-flush.js":"2015-03-20T08:17:34.000Z","build/assets/vendor/seajs/2.0.0/plugin-nocache.js":"2015-03-20T08:17:34.000Z","build/assets/vendor/seajs/2.0.0/plugin-shim.js":"2015-03-20T08:17:34.000Z","build/assets/vendor/seajs/2.0.0/plugin-style.js":"2015-03-20T08:17:34.000Z","build/assets/vendor/seajs/2.0.0/plugin-text.js":"2015-03-20T08:17:34.000Z","build/assets/vendor/seajs/2.0.0/plugin-warning.js":"2015-03-20T08:17:34.000Z","build/assets/vendor/seajs/2.0.0/sea-debug.js":"2015-03-20T08:17:34.000Z","build/assets/vendor/seajs/2.0.0/sea.js":"2015-03-20T08:17:34.000Z","build/assets/vendor/seajs/2.0.0/sea.js.map":"2015-03-20T08:17:34.000Z","build/assets/vendor/seajs/2.0.0/src/bootstrap.js":"2015-03-20T08:17:34.000Z","build/assets/vendor/seajs/2.0.0/src/config.js":"2015-03-20T08:17:34.000Z","build/assets/vendor/seajs/2.0.0/src/intro.js":"2015-03-20T08:17:34.000Z","build/assets/vendor/seajs/2.0.0/src/module.js":"2015-03-20T08:17:34.000Z","build/assets/vendor/seajs/2.0.0/src/outro.js":"2015-03-20T08:17:34.000Z","build/assets/vendor/seajs/2.0.0/src/sea.js":"2015-03-20T08:17:34.000Z","build/assets/vendor/seajs/2.0.0/src/util-deps.js":"2015-03-20T08:17:34.000Z","build/assets/vendor/seajs/2.0.0/src/util-events.js":"2015-03-20T08:17:34.000Z","build/assets/vendor/seajs/2.0.0/src/util-lang.js":"2015-03-20T08:17:34.000Z","build/assets/vendor/seajs/2.0.0/src/util-log.js":"2015-03-20T08:17:34.000Z","build/assets/vendor/seajs/2.0.0/src/util-path.js":"2015-03-20T08:17:34.000Z","build/assets/vendor/seajs/2.0.0/src/util-request.js":"2015-03-20T08:17:34.000Z","build/assets/vendor/seajs/2.0.0/src/plugins/plugin-combo.js":"2015-03-20T08:17:34.000Z","build/assets/vendor/seajs/2.0.0/src/plugins/plugin-debug.js":"2015-03-20T08:17:34.000Z","build/assets/vendor/seajs/2.0.0/src/plugins/plugin-flush.js":"2015-03-20T08:17:34.000Z","build/assets/vendor/seajs/2.0.0/src/plugins/plugin-nocache.js":"2015-03-20T08:17:34.000Z","build/assets/vendor/seajs/2.0.0/src/plugins/plugin-shim.js":"2015-03-20T08:17:34.000Z","build/assets/vendor/seajs/2.0.0/src/plugins/plugin-style.js":"2015-03-20T08:17:34.000Z","build/assets/vendor/seajs/2.0.0/src/plugins/plugin-text.js":"2015-03-20T08:17:34.000Z","build/assets/vendor/seajs/2.0.0/src/plugins/plugin-warning.js":"2015-03-20T08:17:34.000Z","build/assets/vendor/swiper/2.7.0/idangerous.swiper.css":"2015-03-20T08:17:34.000Z","build/assets/vendor/swiper/2.7.0/idangerous.swiper.min.js":"2015-03-20T08:17:34.000Z","build/assets/vendor/ueditor/1.4.3/index.html":"2015-03-20T08:17:35.000Z","build/assets/vendor/ueditor/1.4.3/ueditor.all.js":"2015-03-20T08:17:35.000Z","build/assets/vendor/ueditor/1.4.3/ueditor.all.min.js":"2015-03-20T08:17:35.000Z","build/assets/vendor/ueditor/1.4.3/ueditor.config.js":"2015-03-20T08:17:35.000Z","build/assets/vendor/ueditor/1.4.3/ueditor.parse.js":"2015-03-20T08:17:35.000Z","build/assets/vendor/ueditor/1.4.3/ueditor.parse.min.js":"2015-03-20T08:17:35.000Z","build/assets/vendor/ueditor/1.4.3/dialogs/internal.js":"2015-03-20T08:17:34.000Z","build/assets/vendor/ueditor/1.4.3/dialogs/anchor/anchor.html":"2015-03-20T08:17:34.000Z","build/assets/vendor/ueditor/1.4.3/dialogs/attachment/attachment.css":"2015-03-20T08:17:34.000Z","build/assets/vendor/ueditor/1.4.3/dialogs/attachment/attachment.html":"2015-03-20T08:17:34.000Z","build/assets/vendor/ueditor/1.4.3/dialogs/attachment/attachment.js":"2015-03-20T08:17:34.000Z","build/assets/vendor/ueditor/1.4.3/dialogs/attachment/fileTypeImages/icon_chm.gif":"2015-03-20T08:17:34.000Z","build/assets/vendor/ueditor/1.4.3/dialogs/attachment/fileTypeImages/icon_default.png":"2015-03-20T08:17:34.000Z","build/assets/vendor/ueditor/1.4.3/dialogs/attachment/fileTypeImages/icon_doc.gif":"2015-03-20T08:17:34.000Z","build/assets/vendor/ueditor/1.4.3/dialogs/attachment/fileTypeImages/icon_exe.gif":"2015-03-20T08:17:34.000Z","build/assets/vendor/ueditor/1.4.3/dialogs/attachment/fileTypeImages/icon_jpg.gif":"2015-03-20T08:17:34.000Z","build/assets/vendor/ueditor/1.4.3/dialogs/attachment/fileTypeImages/icon_mp3.gif":"2015-03-20T08:17:34.000Z","build/assets/vendor/ueditor/1.4.3/dialogs/attachment/fileTypeImages/icon_mv.gif":"2015-03-20T08:17:34.000Z","build/assets/vendor/ueditor/1.4.3/dialogs/attachment/fileTypeImages/icon_pdf.gif":"2015-03-20T08:17:34.000Z","build/assets/vendor/ueditor/1.4.3/dialogs/attachment/fileTypeImages/icon_ppt.gif":"2015-03-20T08:17:34.000Z","build/assets/vendor/ueditor/1.4.3/dialogs/attachment/fileTypeImages/icon_psd.gif":"2015-03-20T08:17:34.000Z","build/assets/vendor/ueditor/1.4.3/dialogs/attachment/fileTypeImages/icon_rar.gif":"2015-03-20T08:17:34.000Z","build/assets/vendor/ueditor/1.4.3/dialogs/attachment/fileTypeImages/icon_txt.gif":"2015-03-20T08:17:34.000Z","build/assets/vendor/ueditor/1.4.3/dialogs/attachment/fileTypeImages/icon_xls.gif":"2015-03-20T08:17:34.000Z","build/assets/vendor/ueditor/1.4.3/dialogs/attachment/images/alignicon.gif":"2015-03-20T08:17:34.000Z","build/assets/vendor/ueditor/1.4.3/dialogs/attachment/images/alignicon.png":"2015-03-20T08:17:34.000Z","build/assets/vendor/ueditor/1.4.3/dialogs/attachment/images/bg.png":"2015-03-20T08:17:34.000Z","build/assets/vendor/ueditor/1.4.3/dialogs/attachment/images/file-icons.gif":"2015-03-20T08:17:34.000Z","build/assets/vendor/ueditor/1.4.3/dialogs/attachment/images/file-icons.png":"2015-03-20T08:17:34.000Z","build/assets/vendor/ueditor/1.4.3/dialogs/attachment/images/icons.gif":"2015-03-20T08:17:34.000Z","build/assets/vendor/ueditor/1.4.3/dialogs/attachment/images/icons.png":"2015-03-20T08:17:34.000Z","build/assets/vendor/ueditor/1.4.3/dialogs/attachment/images/image.png":"2015-03-20T08:17:34.000Z","build/assets/vendor/ueditor/1.4.3/dialogs/attachment/images/progress.png":"2015-03-20T08:17:34.000Z","build/assets/vendor/ueditor/1.4.3/dialogs/attachment/images/success.gif":"2015-03-20T08:17:34.000Z","build/assets/vendor/ueditor/1.4.3/dialogs/attachment/images/success.png":"2015-03-20T08:17:34.000Z","build/assets/vendor/ueditor/1.4.3/dialogs/background/background.css":"2015-03-20T08:17:34.000Z","build/assets/vendor/ueditor/1.4.3/dialogs/background/background.html":"2015-03-20T08:17:34.000Z","build/assets/vendor/ueditor/1.4.3/dialogs/background/background.js":"2015-03-20T08:17:34.000Z","build/assets/vendor/ueditor/1.4.3/dialogs/background/images/bg.png":"2015-03-20T08:17:34.000Z","build/assets/vendor/ueditor/1.4.3/dialogs/background/images/success.png":"2015-03-20T08:17:34.000Z","build/assets/vendor/ueditor/1.4.3/dialogs/charts/chart.config.js":"2015-03-20T08:17:34.000Z","build/assets/vendor/ueditor/1.4.3/dialogs/charts/charts.css":"2015-03-20T08:17:34.000Z","build/assets/vendor/ueditor/1.4.3/dialogs/charts/charts.html":"2015-03-20T08:17:34.000Z","build/assets/vendor/ueditor/1.4.3/dialogs/charts/charts.js":"2015-03-20T08:17:34.000Z","build/assets/vendor/ueditor/1.4.3/dialogs/charts/images/charts0.png":"2015-03-20T08:17:34.000Z","build/assets/vendor/ueditor/1.4.3/dialogs/charts/images/charts1.png":"2015-03-20T08:17:34.000Z","build/assets/vendor/ueditor/1.4.3/dialogs/charts/images/charts2.png":"2015-03-20T08:17:34.000Z","build/assets/vendor/ueditor/1.4.3/dialogs/charts/images/charts3.png":"2015-03-20T08:17:34.000Z","build/assets/vendor/ueditor/1.4.3/dialogs/charts/images/charts4.png":"2015-03-20T08:17:34.000Z","build/assets/vendor/ueditor/1.4.3/dialogs/charts/images/charts5.png":"2015-03-20T08:17:34.000Z","build/assets/vendor/ueditor/1.4.3/dialogs/emotion/emotion.css":"2015-03-20T08:17:34.000Z","build/assets/vendor/ueditor/1.4.3/dialogs/emotion/emotion.html":"2015-03-20T08:17:34.000Z","build/assets/vendor/ueditor/1.4.3/dialogs/emotion/emotion.js":"2015-03-20T08:17:34.000Z","build/assets/vendor/ueditor/1.4.3/dialogs/emotion/images/0.gif":"2015-03-20T08:17:34.000Z","build/assets/vendor/ueditor/1.4.3/dialogs/emotion/images/bface.gif":"2015-03-20T08:17:34.000Z","build/assets/vendor/ueditor/1.4.3/dialogs/emotion/images/cface.gif":"2015-03-20T08:17:34.000Z","build/assets/vendor/ueditor/1.4.3/dialogs/emotion/images/fface.gif":"2015-03-20T08:17:34.000Z","build/assets/vendor/ueditor/1.4.3/dialogs/emotion/images/jxface2.gif":"2015-03-20T08:17:34.000Z","build/assets/vendor/ueditor/1.4.3/dialogs/emotion/images/neweditor-tab-bg.png":"2015-03-20T08:17:34.000Z","build/assets/vendor/ueditor/1.4.3/dialogs/emotion/images/tface.gif":"2015-03-20T08:17:34.000Z","build/assets/vendor/ueditor/1.4.3/dialogs/emotion/images/wface.gif":"2015-03-20T08:17:34.000Z","build/assets/vendor/ueditor/1.4.3/dialogs/emotion/images/yface.gif":"2015-03-20T08:17:34.000Z","build/assets/vendor/ueditor/1.4.3/dialogs/gmap/gmap.html":"2015-03-20T08:17:34.000Z","build/assets/vendor/ueditor/1.4.3/dialogs/help/help.css":"2015-03-20T08:17:34.000Z","build/assets/vendor/ueditor/1.4.3/dialogs/help/help.html":"2015-03-20T08:17:34.000Z","build/assets/vendor/ueditor/1.4.3/dialogs/help/help.js":"2015-03-20T08:17:34.000Z","build/assets/vendor/ueditor/1.4.3/dialogs/image/image.css":"2015-03-20T08:17:34.000Z","build/assets/vendor/ueditor/1.4.3/dialogs/image/image.html":"2015-03-20T08:17:34.000Z","build/assets/vendor/ueditor/1.4.3/dialogs/image/image.js":"2015-03-20T08:17:34.000Z","build/assets/vendor/ueditor/1.4.3/dialogs/image/images/alignicon.jpg":"2015-03-20T08:17:34.000Z","build/assets/vendor/ueditor/1.4.3/dialogs/image/images/bg.png":"2015-03-20T08:17:34.000Z","build/assets/vendor/ueditor/1.4.3/dialogs/image/images/icons.gif":"2015-03-20T08:17:34.000Z","build/assets/vendor/ueditor/1.4.3/dialogs/image/images/icons.png":"2015-03-20T08:17:34.000Z","build/assets/vendor/ueditor/1.4.3/dialogs/image/images/image.png":"2015-03-20T08:17:34.000Z","build/assets/vendor/ueditor/1.4.3/dialogs/image/images/progress.png":"2015-03-20T08:17:34.000Z","build/assets/vendor/ueditor/1.4.3/dialogs/image/images/success.gif":"2015-03-20T08:17:34.000Z","build/assets/vendor/ueditor/1.4.3/dialogs/image/images/success.png":"2015-03-20T08:17:34.000Z","build/assets/vendor/ueditor/1.4.3/dialogs/insertframe/insertframe.html":"2015-03-20T08:17:34.000Z","build/assets/vendor/ueditor/1.4.3/dialogs/link/link.html":"2015-03-20T08:17:35.000Z","build/assets/vendor/ueditor/1.4.3/dialogs/map/map.html":"2015-03-20T08:17:35.000Z","build/assets/vendor/ueditor/1.4.3/dialogs/map/show.html":"2015-03-20T08:17:35.000Z","build/assets/vendor/ueditor/1.4.3/dialogs/music/music.css":"2015-03-20T08:17:35.000Z","build/assets/vendor/ueditor/1.4.3/dialogs/music/music.html":"2015-03-20T08:17:35.000Z","build/assets/vendor/ueditor/1.4.3/dialogs/music/music.js":"2015-03-20T08:17:35.000Z","build/assets/vendor/ueditor/1.4.3/dialogs/preview/preview.html":"2015-03-20T08:17:35.000Z","build/assets/vendor/ueditor/1.4.3/dialogs/scrawl/scrawl.css":"2015-03-20T08:17:35.000Z","build/assets/vendor/ueditor/1.4.3/dialogs/scrawl/scrawl.html":"2015-03-20T08:17:35.000Z","build/assets/vendor/ueditor/1.4.3/dialogs/scrawl/scrawl.js":"2015-03-20T08:17:35.000Z","build/assets/vendor/ueditor/1.4.3/dialogs/scrawl/images/addimg.png":"2015-03-20T08:17:35.000Z","build/assets/vendor/ueditor/1.4.3/dialogs/scrawl/images/brush.png":"2015-03-20T08:17:35.000Z","build/assets/vendor/ueditor/1.4.3/dialogs/scrawl/images/delimg.png":"2015-03-20T08:17:35.000Z","build/assets/vendor/ueditor/1.4.3/dialogs/scrawl/images/delimgH.png":"2015-03-20T08:17:35.000Z","build/assets/vendor/ueditor/1.4.3/dialogs/scrawl/images/empty.png":"2015-03-20T08:17:35.000Z","build/assets/vendor/ueditor/1.4.3/dialogs/scrawl/images/emptyH.png":"2015-03-20T08:17:35.000Z","build/assets/vendor/ueditor/1.4.3/dialogs/scrawl/images/eraser.png":"2015-03-20T08:17:35.000Z","build/assets/vendor/ueditor/1.4.3/dialogs/scrawl/images/redo.png":"2015-03-20T08:17:35.000Z","build/assets/vendor/ueditor/1.4.3/dialogs/scrawl/images/redoH.png":"2015-03-20T08:17:35.000Z","build/assets/vendor/ueditor/1.4.3/dialogs/scrawl/images/scale.png":"2015-03-20T08:17:35.000Z","build/assets/vendor/ueditor/1.4.3/dialogs/scrawl/images/scaleH.png":"2015-03-20T08:17:35.000Z","build/assets/vendor/ueditor/1.4.3/dialogs/scrawl/images/size.png":"2015-03-20T08:17:35.000Z","build/assets/vendor/ueditor/1.4.3/dialogs/scrawl/images/undo.png":"2015-03-20T08:17:35.000Z","build/assets/vendor/ueditor/1.4.3/dialogs/scrawl/images/undoH.png":"2015-03-20T08:17:35.000Z","build/assets/vendor/ueditor/1.4.3/dialogs/searchreplace/searchreplace.html":"2015-03-20T08:17:35.000Z","build/assets/vendor/ueditor/1.4.3/dialogs/searchreplace/searchreplace.js":"2015-03-20T08:17:35.000Z","build/assets/vendor/ueditor/1.4.3/dialogs/snapscreen/snapscreen.html":"2015-03-20T08:17:35.000Z","build/assets/vendor/ueditor/1.4.3/dialogs/spechars/spechars.html":"2015-03-20T08:17:35.000Z","build/assets/vendor/ueditor/1.4.3/dialogs/spechars/spechars.js":"2015-03-20T08:17:35.000Z","build/assets/vendor/ueditor/1.4.3/dialogs/table/dragicon.png":"2015-03-20T08:17:35.000Z","build/assets/vendor/ueditor/1.4.3/dialogs/table/edittable.css":"2015-03-20T08:17:35.000Z","build/assets/vendor/ueditor/1.4.3/dialogs/table/edittable.html":"2015-03-20T08:17:35.000Z","build/assets/vendor/ueditor/1.4.3/dialogs/table/edittable.js":"2015-03-20T08:17:35.000Z","build/assets/vendor/ueditor/1.4.3/dialogs/table/edittd.html":"2015-03-20T08:17:35.000Z","build/assets/vendor/ueditor/1.4.3/dialogs/table/edittip.html":"2015-03-20T08:17:35.000Z","build/assets/vendor/ueditor/1.4.3/dialogs/template/config.js":"2015-03-20T08:17:35.000Z","build/assets/vendor/ueditor/1.4.3/dialogs/template/template.css":"2015-03-20T08:17:35.000Z","build/assets/vendor/ueditor/1.4.3/dialogs/template/template.html":"2015-03-20T08:17:35.000Z","build/assets/vendor/ueditor/1.4.3/dialogs/template/template.js":"2015-03-20T08:17:35.000Z","build/assets/vendor/ueditor/1.4.3/dialogs/template/images/bg.gif":"2015-03-20T08:17:35.000Z","build/assets/vendor/ueditor/1.4.3/dialogs/template/images/pre0.png":"2015-03-20T08:17:35.000Z","build/assets/vendor/ueditor/1.4.3/dialogs/template/images/pre1.png":"2015-03-20T08:17:35.000Z","build/assets/vendor/ueditor/1.4.3/dialogs/template/images/pre2.png":"2015-03-20T08:17:35.000Z","build/assets/vendor/ueditor/1.4.3/dialogs/template/images/pre3.png":"2015-03-20T08:17:35.000Z","build/assets/vendor/ueditor/1.4.3/dialogs/template/images/pre4.png":"2015-03-20T08:17:35.000Z","build/assets/vendor/ueditor/1.4.3/dialogs/video/video.css":"2015-03-20T08:17:35.000Z","build/assets/vendor/ueditor/1.4.3/dialogs/video/video.html":"2015-03-20T08:17:35.000Z","build/assets/vendor/ueditor/1.4.3/dialogs/video/video.js":"2015-03-20T08:17:35.000Z","build/assets/vendor/ueditor/1.4.3/dialogs/video/images/bg.png":"2015-03-20T08:17:35.000Z","build/assets/vendor/ueditor/1.4.3/dialogs/video/images/center_focus.jpg":"2015-03-20T08:17:35.000Z","build/assets/vendor/ueditor/1.4.3/dialogs/video/images/file-icons.gif":"2015-03-20T08:17:35.000Z","build/assets/vendor/ueditor/1.4.3/dialogs/video/images/file-icons.png":"2015-03-20T08:17:35.000Z","build/assets/vendor/ueditor/1.4.3/dialogs/video/images/icons.gif":"2015-03-20T08:17:35.000Z","build/assets/vendor/ueditor/1.4.3/dialogs/video/images/icons.png":"2015-03-20T08:17:35.000Z","build/assets/vendor/ueditor/1.4.3/dialogs/video/images/image.png":"2015-03-20T08:17:35.000Z","build/assets/vendor/ueditor/1.4.3/dialogs/video/images/left_focus.jpg":"2015-03-20T08:17:35.000Z","build/assets/vendor/ueditor/1.4.3/dialogs/video/images/none_focus.jpg":"2015-03-20T08:17:35.000Z","build/assets/vendor/ueditor/1.4.3/dialogs/video/images/progress.png":"2015-03-20T08:17:35.000Z","build/assets/vendor/ueditor/1.4.3/dialogs/video/images/right_focus.jpg":"2015-03-20T08:17:35.000Z","build/assets/vendor/ueditor/1.4.3/dialogs/video/images/success.gif":"2015-03-20T08:17:35.000Z","build/assets/vendor/ueditor/1.4.3/dialogs/video/images/success.png":"2015-03-20T08:17:35.000Z","build/assets/vendor/ueditor/1.4.3/dialogs/webapp/webapp.html":"2015-03-20T08:17:35.000Z","build/assets/vendor/ueditor/1.4.3/dialogs/wordimage/fClipboard_ueditor.swf":"2015-03-20T08:17:35.000Z","build/assets/vendor/ueditor/1.4.3/dialogs/wordimage/imageUploader.swf":"2015-03-20T08:17:35.000Z","build/assets/vendor/ueditor/1.4.3/dialogs/wordimage/tangram.js":"2015-03-20T08:17:35.000Z","build/assets/vendor/ueditor/1.4.3/dialogs/wordimage/wordimage.html":"2015-03-20T08:17:35.000Z","build/assets/vendor/ueditor/1.4.3/dialogs/wordimage/wordimage.js":"2015-03-20T08:17:35.000Z","build/assets/vendor/ueditor/1.4.3/lang/en/en.js":"2015-03-20T08:17:35.000Z","build/assets/vendor/ueditor/1.4.3/lang/en/images/addimage.png":"2015-03-20T08:17:35.000Z","build/assets/vendor/ueditor/1.4.3/lang/en/images/alldeletebtnhoverskin.png":"2015-03-20T08:17:35.000Z","build/assets/vendor/ueditor/1.4.3/lang/en/images/alldeletebtnupskin.png":"2015-03-20T08:17:35.000Z","build/assets/vendor/ueditor/1.4.3/lang/en/images/background.png":"2015-03-20T08:17:35.000Z","build/assets/vendor/ueditor/1.4.3/lang/en/images/button.png":"2015-03-20T08:17:35.000Z","build/assets/vendor/ueditor/1.4.3/lang/en/images/copy.png":"2015-03-20T08:17:35.000Z","build/assets/vendor/ueditor/1.4.3/lang/en/images/deletedisable.png":"2015-03-20T08:17:35.000Z","build/assets/vendor/ueditor/1.4.3/lang/en/images/deleteenable.png":"2015-03-20T08:17:35.000Z","build/assets/vendor/ueditor/1.4.3/lang/en/images/listbackground.png":"2015-03-20T08:17:35.000Z","build/assets/vendor/ueditor/1.4.3/lang/en/images/localimage.png":"2015-03-20T08:17:35.000Z","build/assets/vendor/ueditor/1.4.3/lang/en/images/music.png":"2015-03-20T08:17:35.000Z","build/assets/vendor/ueditor/1.4.3/lang/en/images/rotateleftdisable.png":"2015-03-20T08:17:35.000Z","build/assets/vendor/ueditor/1.4.3/lang/en/images/rotateleftenable.png":"2015-03-20T08:17:35.000Z","build/assets/vendor/ueditor/1.4.3/lang/en/images/rotaterightdisable.png":"2015-03-20T08:17:35.000Z","build/assets/vendor/ueditor/1.4.3/lang/en/images/rotaterightenable.png":"2015-03-20T08:17:35.000Z","build/assets/vendor/ueditor/1.4.3/lang/en/images/upload.png":"2015-03-20T08:17:35.000Z","build/assets/vendor/ueditor/1.4.3/lang/zh-cn/zh-cn.js":"2015-03-20T08:17:35.000Z","build/assets/vendor/ueditor/1.4.3/lang/zh-cn/images/copy.png":"2015-03-20T08:17:35.000Z","build/assets/vendor/ueditor/1.4.3/lang/zh-cn/images/localimage.png":"2015-03-20T08:17:35.000Z","build/assets/vendor/ueditor/1.4.3/lang/zh-cn/images/music.png":"2015-03-20T08:17:35.000Z","build/assets/vendor/ueditor/1.4.3/lang/zh-cn/images/upload.png":"2015-03-20T08:17:35.000Z","build/assets/vendor/ueditor/1.4.3/php/Uploader.class.php":"2015-03-20T08:17:35.000Z","build/assets/vendor/ueditor/1.4.3/php/action_crawler.php":"2015-03-20T08:17:35.000Z","build/assets/vendor/ueditor/1.4.3/php/action_list.php":"2015-03-20T08:17:35.000Z","build/assets/vendor/ueditor/1.4.3/php/action_upload.php":"2015-03-20T08:17:35.000Z","build/assets/vendor/ueditor/1.4.3/php/config.json":"2015-03-20T08:17:35.000Z","build/assets/vendor/ueditor/1.4.3/php/controller.php":"2015-03-20T08:17:35.000Z","build/assets/vendor/ueditor/1.4.3/themes/iframe.css":"2015-03-20T08:17:35.000Z","build/assets/vendor/ueditor/1.4.3/themes/default/dialogbase.css":"2015-03-20T08:17:35.000Z","build/assets/vendor/ueditor/1.4.3/themes/default/css/ueditor.css":"2015-03-20T08:17:35.000Z","build/assets/vendor/ueditor/1.4.3/themes/default/css/ueditor.min.css":"2015-03-20T08:17:35.000Z","build/assets/vendor/ueditor/1.4.3/themes/default/images/anchor.gif":"2015-03-20T08:17:35.000Z","build/assets/vendor/ueditor/1.4.3/themes/default/images/arrow.png":"2015-03-20T08:17:35.000Z","build/assets/vendor/ueditor/1.4.3/themes/default/images/arrow_down.png":"2015-03-20T08:17:35.000Z","build/assets/vendor/ueditor/1.4.3/themes/default/images/arrow_up.png":"2015-03-20T08:17:35.000Z","build/assets/vendor/ueditor/1.4.3/themes/default/images/button-bg.gif":"2015-03-20T08:17:35.000Z","build/assets/vendor/ueditor/1.4.3/themes/default/images/cancelbutton.gif":"2015-03-20T08:17:35.000Z","build/assets/vendor/ueditor/1.4.3/themes/default/images/charts.png":"2015-03-20T08:17:35.000Z","build/assets/vendor/ueditor/1.4.3/themes/default/images/cursor_h.gif":"2015-03-20T08:17:35.000Z","build/assets/vendor/ueditor/1.4.3/themes/default/images/cursor_h.png":"2015-03-20T08:17:35.000Z","build/assets/vendor/ueditor/1.4.3/themes/default/images/cursor_v.gif":"2015-03-20T08:17:35.000Z","build/assets/vendor/ueditor/1.4.3/themes/default/images/cursor_v.png":"2015-03-20T08:17:35.000Z","build/assets/vendor/ueditor/1.4.3/themes/default/images/dialog-title-bg.png":"2015-03-20T08:17:35.000Z","build/assets/vendor/ueditor/1.4.3/themes/default/images/filescan.png":"2015-03-20T08:17:35.000Z","build/assets/vendor/ueditor/1.4.3/themes/default/images/highlighted.gif":"2015-03-20T08:17:35.000Z","build/assets/vendor/ueditor/1.4.3/themes/default/images/icons-all.gif":"2015-03-20T08:17:35.000Z","build/assets/vendor/ueditor/1.4.3/themes/default/images/icons.gif":"2015-03-20T08:17:35.000Z","build/assets/vendor/ueditor/1.4.3/themes/default/images/icons.png":"2015-03-20T08:17:35.000Z","build/assets/vendor/ueditor/1.4.3/themes/default/images/loaderror.png":"2015-03-20T08:17:35.000Z","build/assets/vendor/ueditor/1.4.3/themes/default/images/loading.gif":"2015-03-20T08:17:35.000Z","build/assets/vendor/ueditor/1.4.3/themes/default/images/lock.gif":"2015-03-20T08:17:35.000Z","build/assets/vendor/ueditor/1.4.3/themes/default/images/neweditor-tab-bg.png":"2015-03-20T08:17:35.000Z","build/assets/vendor/ueditor/1.4.3/themes/default/images/pagebreak.gif":"2015-03-20T08:17:35.000Z","build/assets/vendor/ueditor/1.4.3/themes/default/images/scale.png":"2015-03-20T08:17:35.000Z","build/assets/vendor/ueditor/1.4.3/themes/default/images/sortable.png":"2015-03-20T08:17:35.000Z","build/assets/vendor/ueditor/1.4.3/themes/default/images/spacer.gif":"2015-03-20T08:17:35.000Z","build/assets/vendor/ueditor/1.4.3/themes/default/images/sparator_v.png":"2015-03-20T08:17:35.000Z","build/assets/vendor/ueditor/1.4.3/themes/default/images/table-cell-align.png":"2015-03-20T08:17:35.000Z","build/assets/vendor/ueditor/1.4.3/themes/default/images/tangram-colorpicker.png":"2015-03-20T08:17:35.000Z","build/assets/vendor/ueditor/1.4.3/themes/default/images/toolbar_bg.png":"2015-03-20T08:17:35.000Z","build/assets/vendor/ueditor/1.4.3/themes/default/images/unhighlighted.gif":"2015-03-20T08:17:35.000Z","build/assets/vendor/ueditor/1.4.3/themes/default/images/upload.png":"2015-03-20T08:17:35.000Z","build/assets/vendor/ueditor/1.4.3/themes/default/images/videologo.gif":"2015-03-20T08:17:35.000Z","build/assets/vendor/ueditor/1.4.3/themes/default/images/word.gif":"2015-03-20T08:17:35.000Z","build/assets/vendor/ueditor/1.4.3/themes/default/images/wordpaste.png":"2015-03-20T08:17:35.000Z","build/assets/vendor/ueditor/1.4.3/third-party/jquery-1.10.2.js":"2015-03-20T08:17:35.000Z","build/assets/vendor/ueditor/1.4.3/third-party/jquery-1.10.2.min.js":"2015-03-20T08:17:35.000Z","build/assets/vendor/ueditor/1.4.3/third-party/jquery-1.10.2.min.map":"2015-03-20T08:17:35.000Z","build/assets/vendor/ueditor/1.4.3/third-party/SyntaxHighlighter/shCore.js":"2015-03-20T08:17:35.000Z","build/assets/vendor/ueditor/1.4.3/third-party/SyntaxHighlighter/shCoreDefault.css":"2015-03-20T08:17:35.000Z","build/assets/vendor/ueditor/1.4.3/third-party/codemirror/codemirror.css":"2015-03-20T08:17:35.000Z","build/assets/vendor/ueditor/1.4.3/third-party/codemirror/codemirror.js":"2015-03-20T08:17:35.000Z","build/assets/vendor/ueditor/1.4.3/third-party/highcharts/highcharts-more.js":"2015-03-20T08:17:35.000Z","build/assets/vendor/ueditor/1.4.3/third-party/highcharts/highcharts-more.src.js":"2015-03-20T08:17:35.000Z","build/assets/vendor/ueditor/1.4.3/third-party/highcharts/highcharts.js":"2015-03-20T08:17:35.000Z","build/assets/vendor/ueditor/1.4.3/third-party/highcharts/highcharts.src.js":"2015-03-20T08:17:35.000Z","build/assets/vendor/ueditor/1.4.3/third-party/highcharts/adapters/mootools-adapter.js":"2015-03-20T08:17:35.000Z","build/assets/vendor/ueditor/1.4.3/third-party/highcharts/adapters/mootools-adapter.src.js":"2015-03-20T08:17:35.000Z","build/assets/vendor/ueditor/1.4.3/third-party/highcharts/adapters/prototype-adapter.js":"2015-03-20T08:17:35.000Z","build/assets/vendor/ueditor/1.4.3/third-party/highcharts/adapters/prototype-adapter.src.js":"2015-03-20T08:17:35.000Z","build/assets/vendor/ueditor/1.4.3/third-party/highcharts/adapters/standalone-framework.js":"2015-03-20T08:17:35.000Z","build/assets/vendor/ueditor/1.4.3/third-party/highcharts/adapters/standalone-framework.src.js":"2015-03-20T08:17:35.000Z","build/assets/vendor/ueditor/1.4.3/third-party/highcharts/modules/annotations.js":"2015-03-20T08:17:35.000Z","build/assets/vendor/ueditor/1.4.3/third-party/highcharts/modules/annotations.src.js":"2015-03-20T08:17:35.000Z","build/assets/vendor/ueditor/1.4.3/third-party/highcharts/modules/canvas-tools.js":"2015-03-20T08:17:35.000Z","build/assets/vendor/ueditor/1.4.3/third-party/highcharts/modules/canvas-tools.src.js":"2015-03-20T08:17:35.000Z","build/assets/vendor/ueditor/1.4.3/third-party/highcharts/modules/data.js":"2015-03-20T08:17:35.000Z","build/assets/vendor/ueditor/1.4.3/third-party/highcharts/modules/data.src.js":"2015-03-20T08:17:35.000Z","build/assets/vendor/ueditor/1.4.3/third-party/highcharts/modules/drilldown.js":"2015-03-20T08:17:35.000Z","build/assets/vendor/ueditor/1.4.3/third-party/highcharts/modules/drilldown.src.js":"2015-03-20T08:17:35.000Z","build/assets/vendor/ueditor/1.4.3/third-party/highcharts/modules/exporting.js":"2015-03-20T08:17:35.000Z","build/assets/vendor/ueditor/1.4.3/third-party/highcharts/modules/exporting.src.js":"2015-03-20T08:17:35.000Z","build/assets/vendor/ueditor/1.4.3/third-party/highcharts/modules/funnel.js":"2015-03-20T08:17:35.000Z","build/assets/vendor/ueditor/1.4.3/third-party/highcharts/modules/funnel.src.js":"2015-03-20T08:17:35.000Z","build/assets/vendor/ueditor/1.4.3/third-party/highcharts/modules/heatmap.js":"2015-03-20T08:17:35.000Z","build/assets/vendor/ueditor/1.4.3/third-party/highcharts/modules/heatmap.src.js":"2015-03-20T08:17:35.000Z","build/assets/vendor/ueditor/1.4.3/third-party/highcharts/modules/map.js":"2015-03-20T08:17:35.000Z","build/assets/vendor/ueditor/1.4.3/third-party/highcharts/modules/map.src.js":"2015-03-20T08:17:35.000Z","build/assets/vendor/ueditor/1.4.3/third-party/highcharts/modules/no-data-to-display.js":"2015-03-20T08:17:35.000Z","build/assets/vendor/ueditor/1.4.3/third-party/highcharts/modules/no-data-to-display.src.js":"2015-03-20T08:17:35.000Z","build/assets/vendor/ueditor/1.4.3/third-party/highcharts/themes/dark-blue.js":"2015-03-20T08:17:35.000Z","build/assets/vendor/ueditor/1.4.3/third-party/highcharts/themes/dark-green.js":"2015-03-20T08:17:35.000Z","build/assets/vendor/ueditor/1.4.3/third-party/highcharts/themes/gray.js":"2015-03-20T08:17:35.000Z","build/assets/vendor/ueditor/1.4.3/third-party/highcharts/themes/grid.js":"2015-03-20T08:17:35.000Z","build/assets/vendor/ueditor/1.4.3/third-party/highcharts/themes/skies.js":"2015-03-20T08:17:35.000Z","build/assets/vendor/ueditor/1.4.3/third-party/video-js/video-js.css":"2015-03-20T08:17:35.000Z","build/assets/vendor/ueditor/1.4.3/third-party/video-js/video-js.min.css":"2015-03-20T08:17:35.000Z","build/assets/vendor/ueditor/1.4.3/third-party/video-js/video-js.swf":"2015-03-20T08:17:35.000Z","build/assets/vendor/ueditor/1.4.3/third-party/video-js/video.dev.js":"2015-03-20T08:17:35.000Z","build/assets/vendor/ueditor/1.4.3/third-party/video-js/video.js":"2015-03-20T08:17:35.000Z","build/assets/vendor/ueditor/1.4.3/third-party/video-js/font/vjs.eot":"2015-03-20T08:17:35.000Z","build/assets/vendor/ueditor/1.4.3/third-party/video-js/font/vjs.svg":"2015-03-20T08:17:35.000Z","build/assets/vendor/ueditor/1.4.3/third-party/video-js/font/vjs.ttf":"2015-03-20T08:17:35.000Z","build/assets/vendor/ueditor/1.4.3/third-party/video-js/font/vjs.woff":"2015-03-20T08:17:35.000Z","build/assets/vendor/ueditor/1.4.3/third-party/webuploader/Uploader.swf":"2015-03-20T08:17:35.000Z","build/assets/vendor/ueditor/1.4.3/third-party/webuploader/webuploader.css":"2015-03-20T08:17:35.000Z","build/assets/vendor/ueditor/1.4.3/third-party/webuploader/webuploader.custom.js":"2015-03-20T08:17:35.000Z","build/assets/vendor/ueditor/1.4.3/third-party/webuploader/webuploader.custom.min.js":"2015-03-20T08:17:35.000Z","build/assets/vendor/ueditor/1.4.3/third-party/webuploader/webuploader.flashonly.js":"2015-03-20T08:17:35.000Z","build/assets/vendor/ueditor/1.4.3/third-party/webuploader/webuploader.flashonly.min.js":"2015-03-20T08:17:35.000Z","build/assets/vendor/ueditor/1.4.3/third-party/webuploader/webuploader.html5only.js":"2015-03-20T08:17:35.000Z","build/assets/vendor/ueditor/1.4.3/third-party/webuploader/webuploader.html5only.min.js":"2015-03-20T08:17:35.000Z","build/assets/vendor/ueditor/1.4.3/third-party/webuploader/webuploader.js":"2015-03-20T08:17:35.000Z","build/assets/vendor/ueditor/1.4.3/third-party/webuploader/webuploader.min.js":"2015-03-20T08:17:35.000Z","build/assets/vendor/ueditor/1.4.3/third-party/webuploader/webuploader.withoutimage.js":"2015-03-20T08:17:35.000Z","build/assets/vendor/ueditor/1.4.3/third-party/webuploader/webuploader.withoutimage.min.js":"2015-03-20T08:17:35.000Z","build/assets/vendor/ueditor/1.4.3/third-party/zeroclipboard/ZeroClipboard.js":"2015-03-20T08:17:35.000Z","build/assets/vendor/ueditor/1.4.3/third-party/zeroclipboard/ZeroClipboard.min.js":"2015-03-20T08:17:35.000Z","build/assets/vendor/ueditor/1.4.3/third-party/zeroclipboard/ZeroClipboard.swf":"2015-03-20T08:17:35.000Z","build/assets/vendor/underscore/underscore-1.4.4.min.js":"2015-03-20T08:17:35.000Z","build/assets/vendor/webuploader/crc32.html":"2015-03-20T08:17:35.000Z","build/assets/vendor/webuploader/crypto-min.js":"2015-03-20T08:17:35.000Z","build/assets/vendor/webuploader/md5.js":"2015-03-20T08:17:35.000Z","build/assets/vendor/webuploader/webuploader.js":"2015-03-20T08:17:35.000Z","build/assets/vendor/webuploader/webuploader.min.js":"2015-03-20T08:17:35.000Z","build/assets/css/doc/amaze.min.css":"2015-03-20T08:17:32.000Z","build/assets/css/doc/amazeui.min.css":"2015-03-20T08:17:32.000Z","build/assets/css/doc/docs.min.css":"2015-03-20T08:17:32.000Z","build/assets/css/doc/embed.default.css":"2015-03-20T08:17:32.000Z","build/assets/igrow/igrow.swiper.js":"2015-03-19T10:44:13.000Z","build/assets/igrow/css/igrow.animate.css":"2015-03-20T08:17:33.000Z","build/assets/igrow/css/igrow.swiper.css":"2015-03-20T08:17:33.000Z","build/assets/igrow/img/public/arrow3.png":"2015-03-20T08:17:33.000Z","build/assets/igrow/img/public/arrow4.png":"2015-03-20T08:17:33.000Z","build/assets/igrow/img/public/arrow5.png":"2015-03-20T08:17:33.000Z","build/assets/igrow/img/public/audio.png":"2015-03-20T08:17:33.000Z","build/assets/igrow/img/public/avatar-80.png":"2015-03-20T08:17:33.000Z","build/assets/igrow/img/public/cmmgc.png":"2015-03-20T08:17:33.000Z","build/assets/igrow/img/public/icon67_status.png":"2015-03-20T08:17:33.000Z","build/assets/igrow/img/public/icon80_smile.png":"2015-03-20T08:17:33.000Z","build/assets/igrow/img/public/img-error.jpg":"2015-03-20T08:17:33.000Z","build/assets/igrow/img/public/loading-128.gif":"2015-03-20T08:17:33.000Z","build/assets/igrow/img/public/loading-32.gif":"2015-03-20T08:17:33.000Z","build/assets/igrow/img/public/no-cover-135.jpg":"2015-03-20T08:17:33.000Z","build/assets/igrow/img/public/video.png":"2015-03-20T08:17:33.000Z","build/assets/igrow/img/swiper/fingerprint.png":"2015-03-20T08:17:33.000Z","build/assets/igrow/img/swiper/music.png":"2015-03-20T08:17:33.000Z","build/assets/igrow/img/swiper/page_nav.png":"2015-03-20T08:17:33.000Z","build/assets/igrow/img/swiper/scan_container.png":"2015-03-20T08:17:33.000Z","build/assets/igrow/img/swiper/scan_line.png":"2015-03-20T08:17:33.000Z","build/assets/igrow/img/swiper/share-bg.png":"2015-03-20T08:17:33.000Z","build/assets/igrow/img/swiper/share-bg1.png":"2015-03-20T08:17:33.000Z","build/assets/igrow/img/swiper/units-icons.png":"2015-03-20T08:17:33.000Z","build/assets/js/controllers/mobile/api.html":"2015-03-19T10:44:13.000Z","build/demos/h5_seed/index.html":"2015-03-19T10:44:14.000Z","build/demos/h5_seed/assets/css/app.css":"2015-03-19T10:44:14.000Z","build/demos/h5_seed/assets/images/1.jpg":"2015-03-19T10:44:14.000Z","build/demos/h5_seed/assets/images/2.jpg":"2015-03-19T10:44:14.000Z","build/demos/h5_seed/assets/images/p1_bg1.jpg":"2015-03-19T10:44:14.000Z","build/demos/h5_seed/assets/images/share.jpg":"2015-03-19T10:44:14.000Z","build/demos/h5_seed/assets/music/bmg.mp3":"2015-03-19T10:44:14.000Z","build/admin/pages/mobile/api.html":"2015-03-20T08:17:35.000Z","build/assets/igrow.zip":"2015-03-20T08:17:33.000Z","build/assets/igrow/swiper.html":"2015-03-20T08:17:33.000Z","build/assets/igrow/widget.html":"2015-03-20T08:17:33.000Z","build/assets/igrow/assets/gfx/gui/checkbox-focus.svg":"2015-03-20T08:17:33.000Z","build/assets/igrow/assets/gfx/gui/checkbox-off.svg":"2015-03-20T08:17:33.000Z","build/assets/igrow/assets/gfx/gui/checkbox-on.svg":"2015-03-20T08:17:33.000Z","build/assets/igrow/assets/gfx/gui/checkbox-partial.svg":"2015-03-20T08:17:33.000Z","build/assets/igrow/assets/gfx/gui/field-error.svg":"2015-03-20T08:17:33.000Z","build/assets/igrow/assets/gfx/gui/field-ok.svg":"2015-03-20T08:17:33.000Z","build/assets/igrow/assets/gfx/gui/radiobutton-focus.svg":"2015-03-20T08:17:33.000Z","build/assets/igrow/assets/gfx/gui/radiobutton-off.svg":"2015-03-20T08:17:33.000Z","build/assets/igrow/assets/gfx/gui/radiobutton-on (1).svg":"2015-03-20T08:17:33.000Z","build/assets/igrow/assets/gfx/gui/radiobutton-on.svg":"2015-03-20T08:17:33.000Z","build/assets/igrow/assets/gfx/gui/select-arrow.svg":"2015-03-20T08:17:33.000Z","build/assets/igrow/assets/gfx1/gui1/checkbox-focus.svg":"2015-03-20T08:17:33.000Z","build/assets/igrow/assets/gfx1/gui1/checkbox-off.svg":"2015-03-20T08:17:33.000Z","build/assets/igrow/assets/gfx1/gui1/checkbox-on.svg":"2015-03-20T08:17:33.000Z","build/assets/igrow/assets/gfx1/gui1/checkbox-partial.svg":"2015-03-20T08:17:33.000Z","build/assets/igrow/assets/gfx1/gui1/field-error.svg":"2015-03-20T08:17:33.000Z","build/assets/igrow/assets/gfx1/gui1/field-ok.svg":"2015-03-20T08:17:33.000Z","build/assets/igrow/assets/gfx1/gui1/radiobutton-focus.svg":"2015-03-20T08:17:33.000Z","build/assets/igrow/assets/gfx1/gui1/radiobutton-off.svg":"2015-03-20T08:17:33.000Z","build/assets/igrow/assets/gfx1/gui1/radiobutton-on (1).svg":"2015-03-20T08:17:33.000Z","build/assets/igrow/assets/gfx1/gui1/radiobutton-on.svg":"2015-03-20T08:17:33.000Z","build/assets/igrow/assets/gfx1/gui1/select-arrow.svg":"2015-03-20T08:17:33.000Z","build/assets/igrow/assets/imobile/css/animate.css":"2015-03-20T08:17:33.000Z","build/assets/igrow/assets/imobile/css/beautiful.css":"2015-03-20T08:17:33.000Z","build/assets/igrow/assets/imobile/css/gray.svg":"2015-03-20T08:17:33.000Z","build/assets/igrow/assets/imobile/css/imobile.css":"2015-03-20T08:17:33.000Z","build/assets/igrow/assets/imobile/images/arrow-down.png":"2015-03-20T08:17:33.000Z","build/assets/igrow/assets/imobile/images/arrow-right.png":"2015-03-20T08:17:33.000Z","build/assets/igrow/assets/imobile/images/arrow-up.png":"2015-03-20T08:17:33.000Z","build/assets/igrow/assets/imobile/images/audio.png":"2015-03-20T08:17:33.000Z","build/assets/igrow/assets/imobile/images/avatar-80.png":"2015-03-20T08:17:33.000Z","build/assets/igrow/assets/imobile/images/base_z2254d3.png":"2015-03-20T08:17:33.000Z","build/assets/igrow/assets/imobile/images/icon67_status.png":"2015-03-20T08:17:33.000Z","build/assets/igrow/assets/imobile/images/icon80_smile.png":"2015-03-20T08:17:33.000Z","build/assets/igrow/assets/imobile/images/img-error.jpg":"2015-03-20T08:17:33.000Z","build/assets/igrow/assets/imobile/images/landscape-bg.png":"2015-03-20T08:17:33.000Z","build/assets/igrow/assets/imobile/images/landscape-phone.png":"2015-03-20T08:17:33.000Z","build/assets/igrow/assets/imobile/images/loading-32.gif":"2015-03-20T08:17:33.000Z","build/assets/igrow/assets/imobile/images/loading.gif":"2015-03-20T08:17:33.000Z","build/assets/igrow/assets/imobile/images/no-cover-135.jpg":"2015-03-20T08:17:33.000Z","build/assets/igrow/assets/imobile/images/photo-selected.png":"2015-03-20T08:17:33.000Z","build/assets/igrow/assets/imobile/images/select-arrow.svg":"2015-03-20T08:17:33.000Z","build/assets/igrow/assets/imobile/images/share-bg.png":"2015-03-20T08:17:33.000Z","build/assets/igrow/assets/imobile/images/success.png":"2015-03-20T08:17:33.000Z","build/assets/igrow/assets/imobile/images/units-icons.png":"2015-03-20T08:17:33.000Z","build/assets/igrow/assets/imobile/images/video.png":"2015-03-20T08:17:33.000Z","build/assets/igrow/assets/imobile/images/分享.png":"2015-03-20T08:17:33.000Z","build/assets/igrow/assets/imobile/js/imobile.js":"2015-03-20T08:17:33.000Z","build/assets/igrow/assets/imobile/js/zMobile.js":"2015-03-20T08:17:33.000Z","build/assets/igrow/assets/imobile/js/widgets/load.js":"2015-03-20T08:17:33.000Z","build/assets/igrow/assets/music/bmg.mp3":"2015-03-20T08:17:33.000Z","build/assets/igrow/assets/public/igrow.util.js":"2015-03-20T08:17:33.000Z","build/assets/igrow/assets/public/sizzle.js":"2015-03-20T08:17:33.000Z","build/assets/igrow/assets/public/utils.js":"2015-03-20T08:17:33.000Z","build/assets/igrow/img/swiper/landscape-phone.png":"2015-03-20T08:17:33.000Z","build/assets/igrow/js/igrow.swiper.js":"2015-03-20T08:17:33.000Z","build/assets/plugins/ZeroClipboard.min.js":"2015-03-20T08:17:34.000Z","build/admin/pages/mobile/animate.html":"2015-03-20T08:17:35.000Z","build/admin/pages/mobile/img/p1_cartoon.png":"2015-03-20T08:17:35.000Z","build/admin/pages/mobile/img/sleep/preface_page.png":"2015-03-20T08:17:35.000Z","build/admin/pages/mobile/img/sleep/star_v150311132540.png":"2015-03-20T08:17:35.000Z","build/assets/i/app-icon72x72@2x.png":"2015-03-20T08:17:33.000Z"}